Workbook

Sheet AMP Dealer Profile Data
A1: DEALER_CD | B1: DEALER_NAME | C1: AMP_HIERARCHY_ID | D1: DEALER_PHONE | E1: DEALER_ADDRESS | F1: DEALER_CITY | G1: DEALER_STATE | H1: DEALER_ZIP | I1: DEALER_URL | J1: DEALER_ADDTLSERVICES | K1: DEALER_SERVICE_URL | L1: DEALER_HOURS | M1: EMAIL_REPLY_TO | N1: SERVICE_MANAGER_NAME | O1: SIGNATURE_LINE_1 | P1: SIGNATURE_LINE_2 | Q1: ENGAGE_ENROLLMENT_STATUS | R1: AMENITY_1 | S1: AMENITY_2 | T1: AMENITY_3 | U1: AMENITY_4 | V1: AMENITY_5 | W1: AMENITY_6 | X1: SALES_PHONE | Y1: FACEBOOK_URL | Z1: TWITTER_URL | AA1: YOUTUBE_URL | AB1: YELP_URL | AC1: INSTAGRAM_URL | AD1: ECOMMERCE_URL | AE1: TIRE_CENTER_URL | AF1: ADDED_DATE | AG1: UPDATED_DATE | AH1: Error_Type | AI1: Notes | AJ1: Suggested_New_URL | AK1: Suggested_URL_Confidence
A2: 09163 | B2: Headquarter Toyota | C2: 50A | D2: 305-364-9800 | E2: 5895 N.W. 167th Street | F2: Hialeah | G2: FL | H2: 33015 | I2: https://www.headquartertoyota.com | J2: Spanish Speaking;Parts Center;Toyota Collision Center;Toyota Tire Center | K2: https://www.headquartertoyota.com/schedule-appointment.html | L2: Monday 7:00 am - 8:00 pm~Tuesday 7:00 am - 8:00 pm~Wednesday 7:00 am - 8:00 pm~Thursday 7:00 am - 8:00 pm~Friday 7:00 am - 8:00 pm~Saturday 7:30 am - 5:00 pm~Sunday 8:00 am - 3:00 pm | M2: barbara.damon@headquartertoyota.com | R2: Spanish Speaking | X2: 3053649800 | Y2: https://www.facebook.com/HeadquarterToyota | Z2: https://twitter.com/hqtoyota | AA2: https://www.youtube.com/user/HeadquarterToyota/about | AB2: https://www.yelp.com/biz/headquarter-toyota-miami | AC2: https://instagram.com/headquartertoyota | AE2: https://www.settirecenters.com/?uid=B78F523B-43EA-46DD-8AB01481E700187B | AF2: 2022-04-11 | AG2: 2026-01-06 | AH2: No Issue Detected
A3: 09168 | B3: Gettel Toyota of Bradenton | C3: 50B | D3: 941-756-5511 | E3: 6323 14th Street West | F3: Bradenton | G3: FL | H3: 34207 | I3: https://www.getteltoyotaofbradenton.com | J3: Spanish Speaking;Express Maintenance;Parts Center;Toyota Collision Center;Toyota Tire Center;Pres. Customer 1st Award | K3: https://www.getteltoyotaofbradenton.com/service-center-schedule-service.html | L3: Monday 7:00 am - 6:00 pm~Tuesday 7:00 am - 6:00 pm~Wednesday 7:00 am - 6:00 pm~Thursday 7:00 am - 6:00 pm~Friday 7:00 am - 6:00 pm~Saturday 7:00 am - 4:00 pm~Sunday 8:00 am - 2:00 pm | M3: jgorrill@gettel.com | R3: Spanish Speaking | X3: 9417565511 | Y3: https://www.facebook.com/getteltoyotaofbradenton | Z3: https://twitter.com/GettelToyota | AA3: https://www.youtube.com/channel/UCODmpNz8MoCNAgDB_pCrUMA/about | AB3: https://www.yelp.com/biz/gettel-toyota-bradenton | AE3: https://www.settirecenters.com/?uid=F454BAC3-B04D-47A3-909631D3F24A4388 | AF3: 2022-04-11 | AG3: 2026-05-06 | AH3: Unreachable / Timeout | AI3: ('Connection aborted.', RemoteDisconnected('Remote end closed connection without response')) | browser fallback unavailable: Page.goto: Timeout 20000ms exceeded. Call log: - navigating to "https://w
A4: 09216 | B4: West Kendall Toyota | C4: 50A | D4: 786-573-5900 | E4: 13800 SW 137th Avenue | F4: Miami | G4: FL | H4: 33186 | I4: https://www.westkendalltoyota.com | J4: Spanish Speaking;Express Maintenance;Off-Site Service Center;Toyota Tire Center | K4: https://www.westkendalltoyota.com/service/schedule-service/ | L4: Monday 7:00 am - 8:00 pm~Tuesday 7:00 am - 8:00 pm~Wednesday 7:00 am - 8:00 pm~Thursday 7:00 am - 8:00 pm~Friday 7:00 am - 8:00 pm~Saturday 7:00 am - 6:00 pm~Sunday 8:00 am - 3:00 pm | M4: karina.mair@westkendalltoyota.com | R4: Spanish Speaking | X4: 7863452600 | Y4: https://www.facebook.com/WestKendallToyota | Z4: https://twitter.com/WKendallToyota | AA4: https://www.youtube.com/user/WestKendallToyota/about | AB4: https://www.yelp.com/biz/west-kendall-toyota-sales-miami | AC4: https://instagram.com/westkendalltoyota | AE4: https://www.settirecenters.com/?uid=7B83A0E4-9506-4E6A-A5FF727D97A1972A | AF4: 2022-04-11 | AG4: 2026-05-06 | AH4: No Issue Detected
A5: 09218 | B5: Toyota of Melbourne | C5: 50C | D5: 321-254-8888 | E5: 24 North Harbor City Blvd | F5: Melbourne | G5: FL | H5: 32935 | I5: https://www.toyotaofmelbourne.com | J5: Spanish Speaking;Express Maintenance;Parts Center;Toyota Collision Center;Toyota Tire Center | K5: https://www.toyotaofmelbourne.com/service-center-schedule-service.html | L5: Monday 7:00 am - 7:00 pm~Tuesday 7:00 am - 7:00 pm~Wednesday 7:00 am - 7:00 pm~Thursday 7:00 am - 7:00 pm~Friday 7:00 am - 7:00 pm~Saturday 7:00 am - 4:00 pm~ | M5: klopez@toyotaofmelbourne.com | R5: Spanish Speaking | X5: 3212548888 | Y5: https://www.facebook.com/ToyotaOfMelbourne | Z5: https://twitter.com/toyotamelb | AA5: https://www.youtube.com/user/ToyotaMelbourne | AB5: https://www.yelp.com/biz/toyota-of-melbourne-melbourne-2 | AC5: https://instagram.com/toyotamelbourne | AE5: https://www.settirecenters.com/?uid=3473A2D2-410D-4DFE-A64D90B19F938FBF | AF5: 2022-04-11 | AG5: 2026-07-07 | AH5: Error Page Entered | AI5: Status 403 at https://www.toyotaofmelbourne.com/service-center-schedule-service.html | AK5: None (no sitemap found; homepage links yielded no candidates)
A6: 09239 | B6: Gettel Toyota of Charlotte County | C6: 50B | D6: 941-639-1155 | E6: 1801 Tamiami Trail | F6: Punta Gorda | G6: FL | H6: 33950 | I6: https://www.getteltoyotaofcharlottecounty.com | J6: Express Maintenance;Toyota Collision Center | K6: https://www.getteltoyotaofcharlottecounty.com/schedule-service-appointment.html | L6: Monday 7:00 am - 6:00 pm~Tuesday 7:00 am - 6:00 pm~Wednesday 7:00 am - 6:00 pm~Thursday 7:00 am - 6:00 pm~Friday 7:00 am - 6:00 pm~Saturday 7:00 am - 5:00 pm~ | X6: 9416391155 | AE6: https://www.settirecenters.com/?uid=344AD954-7D72-45F6-B08CEDC17960E29F | AF6: 2022-04-11 | AG6: 2026-06-08 | AH6: Redirect Drops Query String | AI6: https://www.getteltoyotaofcharlottecounty.com/schedule-service-appointment.html -> https://www.getteltoyotaofcharlottecounty.com/service/schedule-service/ (redirect drops query strings; confirmed by appending test params: https://www.getteltoyotaofcharlottecounty.com/schedule-service-appointment.html?siteid=test&utm_source=test -> https://www.getteltoyotaofcharlottecounty.com/service/schedule-service/)
A7: 09245 | B7: Sebring Toyota | C7: 50C | D7: 863-225-8576 | E7: 404 U.S. Highway 27 North | F7: Sebring | G7: FL | H7: 33870 | I7: https://www.sebringtoyota.com | K7: https://www.sebringtoyota.com/service/index.htm | L7: Monday 7:00 am - 6:00 pm~Tuesday 7:00 am - 6:00 pm~Wednesday 7:00 am - 6:00 pm~Thursday 7:00 am - 6:00 pm~Friday 7:00 am - 6:00 pm~Saturday 8:00 am - 4:00 pm~ | X7: 8633851525 | AE7: https://www.settirecenters.com/?uid=5220820A-B629-4BE4-8D0F1C031A53DD59 | AF7: 2022-06-30 | AG7: 2026-07-07 | AH7: Redirect Drops Query String | AI7: https://www.sebringtoyota.com/service/index.htm -> https://www.sebringtoyota.com/schedule-service.htm (redirect drops query strings; confirmed by appending test params: https://www.sebringtoyota.com/service/index.htm?siteid=test&utm_source=test -> https://www.sebringtoyota.com/schedule-service.htm)
A8: 10015 | B8: Milton Martin Toyota | C8: 50H | D8: 770-535-0778 | E8: 3150 Milton Martin Toyota Way | F8: Gainesville | G8: GA | H8: 30507 | I8: https://www.miltonmartintoyota.com | J8: 24-Hour Vehicle Drop Off;Advanced Diagnostics;Advanced Tune-Up Equip.;Barista/Coffee Bar;Children's Play Area;Complimentary Beverages;Express Maintenance;Toyota Collision Center;Toyota Tire Center;Pres. Customer 1st Award | K8: https://www.miltonmartintoyota.com/service/schedule-service/ | L8: Monday 7:00 am - 6:00 pm~Tuesday 7:00 am - 6:00 pm~Wednesday 7:00 am - 6:00 pm~Thursday 7:00 am - 6:00 pm~Friday 7:00 am - 6:00 pm~Saturday 7:00 am - 5:00 pm~ | R8: 24-Hour Vehicle Drop Off | S8: Advanced Diagnostics | T8: Advanced Tune-Up Equip. | U8: Barista/Coffee Bar | V8: Children's Play Area | W8: Complimentary Beverages | X8: 7705324355 | Y8: https://www.facebook.com/MMToyota/ | Z8: https://twitter.com/mmartintoyota | AA8: https://www.youtube.com/user/miltonmartintoyota1 | AB8: https://www.yelp.com/biz/milton-martin-toyota-gainesville | AE8: https://www.settirecenters.com/?uid=44AB4EF9-E8C2-4A2D-BED81B3E09F036B4 | AF8: 2022-04-11 | AG8: 2026-06-08 | AH8: No Issue Detected
A9: 10035 | B9: North Georgia Toyota | C9: 50F | D9: 706-659-0475 | E9: 1510 East Walnut Avenue | F9: Dalton | G9: GA | H9: 30721 | I9: https://www.northgeorgiatoyota.com | J9: Express Maintenance;Toyota Collision Center;Toyota Tire Center | K9: https://www.northgeorgiatoyota.com/service/schedule-service/ | L9: Monday 7:30 am - 6:00 pm~Tuesday 7:30 am - 6:00 pm~Wednesday 7:30 am - 6:00 pm~Thursday 7:30 am - 6:00 pm~Friday 7:30 am - 6:00 pm~Saturday 8:00 am - 3:00 pm~ | X9: 7062781322 | Y9: https://www.facebook.com/northgeorgiatoyota | Z9: https://twitter.com/northgatoyota | AA9: https://www.youtube.com/user/NorthGAToyota | AB9: https://www.yelp.com/biz/north-georgia-toyota-dalton | AC9: https://www.instagram.com/northgatoyota | AE9: https://www.settirecenters.com/?uid=434DFB5E-E090-4FC2-8D42EBA03F2E5BFD | AF9: 2022-04-11 | AG9: 2026-05-06 | AH9: No Issue Detected
A10: 10040 | B10: Prince Toyota | C10: 50D | D10: 229-353-0039 | E10: 2013 U.S. Highway 82 West | F10: Tifton | G10: GA | H10: 31793 | I10: https://www.princetoyota.com | J10: Toyota Tire Center | K10: https://www.princetoyota.com/schedule-service | L10: Monday 7:30 am - 6:00 pm~Tuesday 7:30 am - 6:00 pm~Wednesday 7:30 am - 6:00 pm~Thursday 7:30 am - 6:00 pm~Friday 7:30 am - 6:00 pm~Saturday 8:00 am - 2:00 pm~ | X10: 2293864000 | Y10: https://www.facebook.com/PrinceToyotaTifton | Z10: https://twitter.com/PrinceToyotaTif | AA10: https://www.youtube.com/user/princetoyotatifton | AB10: https://www.yelp.com/biz/prince-toyota-tifton | AC10: https://instagram.com/princetoyotatifton | AE10: https://www.settirecenters.com/?uid=BC926DA3-4707-4BD1-B2F86527FFAF7265 | AF10: 2022-04-11 | AG10: 2026-06-08 | AH10: No Issue Detected
A11: 10118 | B11: Nalley Toyota of Roswell | C11: 50H | D11: 770-763-7398 | E11: 11130 Alpharetta Highway | F11: Roswell | G11: GA | H11: 30076 | I11: https://www.toyotaofroswell.com | J11: 24-Hour Vehicle Drop Off;Advanced Diagnostics;Online Scheduling;Toyota Cert. Technicians;WiFi Available;Car Wash;Express Lube;Express Maintenance;Parts Center;Toyota Collision Center;Toyota Tire Center | K11: https://www.toyotaofroswell.com/service/schedule-appointment.htm | L11: Monday 7:00 am - 7:00 pm~Tuesday 7:00 am - 7:00 pm~Wednesday 7:00 am - 7:00 pm~Thursday 7:00 am - 7:00 pm~Friday 7:00 am - 7:00 pm~Saturday 7:00 am - 5:00 pm~ | R11: 24-Hour Vehicle Drop Off | S11: Advanced Diagnostics | T11: Online Scheduling | U11: Toyota Cert. Technicians | V11: WiFi Available | X11: 7705948696 | Y11: https://www.facebook.com/NalleyToyotaScionRoswell | Z11: https://x.com/nalleytoysci | AA11: https://www.youtube.com/@NalleyToyotaofRoswell | AC11: https://www.instagram.com/nalleytoyotaroswell | AE11: https://www.settirecenters.com/?uid=7A554FCC-7600-4AF7-A51731A4F89AA670 | AF11: 2022-04-11 | AG11: 2026-06-08 | AH11: No Issue Detected
A12: 10128 | B12: Five Star Toyota of Milledgeville | C12: 50G | D12: 478-453-9451 | E12: 2816 North Columbia Street | F12: Milledgeville | G12: GA | H12: 31061 | I12: https://www.fivestartoyotaofmilledgeville.com | K12: https://www.fivestartoyotaofmilledgeville.com/schedule-service-appointment.html | L12: Monday 7:30 am - 6:00 pm~Tuesday 7:30 am - 6:00 pm~Wednesday 7:30 am - 6:00 pm~Thursday 7:30 am - 6:00 pm~Friday 7:30 am - 6:00 pm~Saturday 8:00 am - 2:00 pm~ | X12: 4784539451 | Y12: https://www.facebook.com/fivestartoyotaofmilledgeville | Z12: https://twitter.com/ToyotaScionGA | AA12: https://www.youtube.com/user/louieherrontoyota | AB12: https://www.yelp.com/biz/louie-herron-toyota-milledgeville | AE12: https://www.settirecenters.com/?uid=F9BB1EB2-EAD8-456A-A481D763E1929CEE | AF12: 2022-04-11 | AG12: 2026-06-08 | AH12: Error Page Entered | AI12: Status 404 at https://www.fivestartoyotaofmilledgeville.com/schedule-service-appointment.html | AJ12: https://www.fivestartoyotaofmilledgeville.com/vehicle-finder-service/ | AK12: High
A13: 10130 | B13: Beaver Toyota of Cumming | C13: 50H | D13: 470-533-2000 | E13: 1875 Buford Highway | F13: Cumming | G13: GA | H13: 30041 | I13: https://www.beavertoyotacumming.com | J13: 24-Hour Vehicle Drop Off;Advanced Diagnostics;Advanced Tune-Up Equip.;Barista/Coffee Bar;Children's Play Area;Complimentary Beverages;Car Wash;Express Lube;Express Maintenance;On-Site Rental Vehicles;Toyota Collision Center;Pres. Customer 1st Award | K13: https://www.beavertoyotacumming.com/service/schedule-service/ | L13: Monday 7:00 am - 6:00 pm~Tuesday 7:00 am - 6:00 pm~Wednesday 7:00 am - 6:00 pm~Thursday 7:00 am - 6:00 pm~Friday 7:00 am - 6:00 pm~Saturday 7:00 am - 5:00 pm~ | M13: btcservicebdc@beavertoyota.com | N13: Chris Calavan | O13: We're here to WOW ya! | R13: 24-Hour Vehicle Drop Off | S13: Advanced Diagnostics | T13: Advanced Tune-Up Equip. | U13: Barista/Coffee Bar | V13: Children's Play Area | W13: Complimentary Beverages | X13: 4705332000 | Y13: https://www.facebook.com/beavertoyotacumming/ | AA13: https://www.youtube.com/c/BeaverToyotaofCumming/videos | AC13: https://www.instagram.com/beavertoyotacumming/?hl=en | AE13: https://www.settirecenters.com/?uid=C1F18A82-9DB9-4A2B-ABFD2BD10983D84F | AF13: 2022-04-11 | AG13: 2026-07-07 | AH13: No Issue Detected
A14: 10131 | B14: Stone Mountain Toyota | C14: 50H | D14: 770-736-0159 | E14: 4220 Stone Mountain Highway | F14: Lilburn | G14: GA | H14: 30047 | I14: https://www.stonemountaintoyota.com | J14: Spanish Speaking | K14: https://stonemountaintoyota.com/schedule-service | L14: Monday 7:00 am - 7:00 pm~Tuesday 7:00 am - 7:00 pm~Wednesday 7:00 am - 7:00 pm~Thursday 7:00 am - 7:00 pm~Friday 7:00 am - 7:00 pm~Saturday 7:00 am - 5:00 pm~ | R14: Spanish Speaking | X14: 7707360030 | AE14: https://www.settirecenters.com/?uid=CF653515-ECBF-446E-99D9CE7298E4DD6C | AF14: 2022-04-11 | AG14: 2026-06-08 | AH14: Unreachable / Timeout | AI14: ('Connection aborted.', RemoteDisconnected('Remote end closed connection without response')) | browser fallback unavailable: Page.goto: Timeout 20000ms exceeded. Call log: - navigating to "https://s
A15: 10132 | B15: Nalley Toyota Union City | C15: 50H | D15: 770-284-8361 | E15: 4115 Jonesboro Road | F15: Union City | G15: GA | H15: 30291 | I15: https://www.toyotaofunioncity.com | K15: https://www.toyotaofunioncity.com/service/schedule-appointment.htm | L15: Monday 7:00 am - 6:00 pm~Tuesday 7:00 am - 6:00 pm~Wednesday 7:00 am - 6:00 pm~Thursday 7:00 am - 6:00 pm~Friday 7:00 am - 6:00 pm~Saturday 7:00 am - 4:00 pm~ | X15: 7709648888 | AE15: https://www.settirecenters.com/?uid=CB376CA3-E3D4-4F3B-9A9B6C2F4AB587FE | AF15: 2022-04-11 | AG15: 2026-07-07 | AH15: No Issue Detected
A16: 10138 | B16: Krause Toyota South Atlanta | C16: 50H | D16: 770-961-0225 | E16: 6865 Jonesboro Road | F16: Morrow | G16: GA | H16: 30260 | I16: https://www.krausetoyotasouthatlanta.com | L16: Monday 7:00 am - 7:00 pm~Tuesday 7:00 am - 7:00 pm~Wednesday 7:00 am - 7:00 pm~Thursday 7:00 am - 7:00 pm~Friday 7:00 am - 7:00 pm~Saturday 7:00 am - 5:00 pm~ | X16: 7709610225 | AE16: https://www.settirecenters.com/?uid=F20ED9D1-614B-46F1-8531FF416AB3877E | AF16: 2026-07-02 | AG16: 2026-07-07 | AH16: No URL | AJ16: https://www.krausetoyotasouthatlanta.com/service/toyota-maintenance-schedule/ | AK16: High
A17: 10139 | B17: Group 1 Toyota Stone Mountain | C17: 50H | D17: 770-736-0030 | E17: 4220 Stone Mountain Highway | F17: Lilburn | G17: GA | H17: 30047 | I17: https://www.group1toyotastonemountain.com | L17: Monday 7:00 am - 7:00 pm~Tuesday 7:00 am - 7:00 pm~Wednesday 7:00 am - 7:00 pm~Thursday 7:00 am - 7:00 pm~Friday 7:00 am - 7:00 pm~Saturday 7:00 am - 5:00 pm~ | X17: 7707360030 | AE17: https://www.settirecenters.com/?uid=CF653515-ECBF-446E-99D9CE7298E4DD6C | AF17: 2026-07-02 | AG17: 2026-07-07 | AH17: No URL | AJ17: https://www.group1toyotastonemountain.com/service/schedule-service/ | AK17: High
A18: 11011 | B18: Stone's Town and Country Toyota | C18: 136 | D18: 208-356-9366 | E18: 615 S. Yellowstone Highway | F18: Rexburg | G18: ID | H18: 83440 | I18: https://www.stonestoyota.com | J18: 24-Hour Vehicle Drop Off;Advanced Diagnostics;Advanced Tune-Up Equip.;Barista/Coffee Bar;Children's Play Area;Complimentary Beverages;Car Wash;Express Lube;Parts Center;Toyota Tire Center | K18: https://www.stonestoyota.com/toyota-schedule-service/ | L18: Monday 7:30 am - 6:00 pm~Tuesday 7:30 am - 6:00 pm~Wednesday 7:30 am - 6:00 pm~Thursday 7:30 am - 6:00 pm~Friday 7:30 am - 6:00 pm~Saturday 9:00 am - 5:00 pm~ | R18: 24-Hour Vehicle Drop Off | S18: Advanced Diagnostics | T18: Advanced Tune-Up Equip. | U18: Barista/Coffee Bar | V18: Children's Play Area | W18: Complimentary Beverages | X18: 2083569366 | Y18: https://www.facebook.com/stonestoyota | Z18: https://twitter.com/stonestoyota | AB18: https://www.yelp.com/biz/stones-toyota-rexburg | AE18: https://www.toyotatirecenter.com/?uid=688EB5EC-A04C-4526-ADDA64A089DBA0D5 | AF18: 2022-04-11 | AG18: 2026-06-08 | AH18: Error Page Entered | AI18: Status 403 at https://www.stonestoyota.com/toyota-schedule-service/ | AK18: None (no sitemap found; homepage links yielded no candidates)
A19: 04277 | B19: North Bakersfield Toyota | C19: 118 | D19: 661-218-1679 | E19: 19651 Industry Prkwy Dr. | F19: Bakersfield | G19: CA | H19: 93308 | I19: https://www.northbakersfieldtoyota.com | J19: 24-Hour Vehicle Drop Off;Advanced Diagnostics;Complimentary Ride Share;EV Charging Station;Late Pickup;Online Scheduling;Car Wash;On-Site Rental Vehicles;Parts Center;Toyota Tire Center | K19: https://www.northbakersfieldtoyota.com/service/schedule-service/ | L19: Monday 7:00 am - 6:00 pm~Tuesday 7:00 am - 6:00 pm~Wednesday 7:00 am - 6:00 pm~Thursday 7:00 am - 6:00 pm~Friday 7:00 am - 6:00 pm~Saturday 7:00 am - 4:00 pm~ | N19: Jason Cronin | O19: Jason Cronin | P19: Service Manager | R19: 24-Hour Vehicle Drop Off | S19: Advanced Diagnostics | T19: Complimentary Ride Share | U19: EV Charging Station | V19: Late Pickup | W19: Online Scheduling | X19: 6616151100 | Y19: https://www.facebook.com/northbakersfieldtoyota/ | AA19: https://www.youtube.com/user/NBT04528 | AC19: https://www.instagram.com/north_bakersfield_toyota/ | AE19: https://www.toyotatirecenter.com/?uid=8764EBAB-9323-DE24-1ADE8F44AEACA74C | AF19: 2022-04-11 | AG19: 2025-12-19 | AH19: No Issue Detected
A20: 04284 | B20: Claremont Toyota | C20: 115 | D20: 909-542-1687 | E20: 601 Auto Center Drive | F20: Claremont | G20: CA | H20: 91711 | I20: https://www.claremonttoyota.com | J20: 24-Hour Vehicle Drop Off;Advanced Diagnostics;Advanced Tune-Up Equip.;Complimentary Beverages;Complimentary Ride Share;EV Charging Station;Auto Detailing;Express Lube;Express Maintenance;On-Site Rental Vehicles;Parts Center;Toyota Tire Center;Board of Governors Award;Pres. Customer 1st Award | K20: https://www.claremonttoyota.com/#modal-scheduleservice | L20: Monday 7:00 am - 7:00 pm~Tuesday 7:00 am - 7:00 pm~Wednesday 7:00 am - 7:00 pm~Thursday 7:00 am - 7:00 pm~Friday 7:00 am - 7:00 pm~Saturday 7:00 am - 5:00 pm~ | O20: Your Claremont Service Team | R20: 24-Hour Vehicle Drop Off | S20: Advanced Diagnostics | T20: Advanced Tune-Up Equip. | U20: Complimentary Beverages | V20: Complimentary Ride Share | W20: EV Charging Station | X20: 9096251500 | AE20: https://www.toyotatirecenter.com/?uid=F8C50940-990C-D256-B20C1B811C70100D | AF20: 2022-04-11 | AG20: 2026-05-06 | AH20: Same as Dealer_URL (homepage) | AJ20: https://www.claremonttoyota.com/inventory-cpo.json | AK20: Medium
A21: 04294 | B21: United Toyota | C21: 114 | D21: 760-457-0212 | E21: 2351 Highway 86 | F21: Imperial | G21: CA | H21: 92251 | I21: https://www.unitedtoyotaimperial.com | J21: 24-Hour Vehicle Drop Off;Advanced Diagnostics;Advanced Tune-Up Equip.;Children's Play Area;Online Scheduling;Pet Friendly | K21: https://www.unitedtoyotaimperial.com/service/ | L21: Monday 7:00 am - 6:00 pm~Tuesday 7:00 am - 6:00 pm~Wednesday 7:00 am - 6:00 pm~Thursday 7:00 am - 6:00 pm~Friday 7:00 am - 6:00 pm~Saturday 7:00 am - 6:00 pm~ | M21: service@unitedtoyotaimperial.com | R21: 24-Hour Vehicle Drop Off | S21: Advanced Diagnostics | T21: Advanced Tune-Up Equip. | U21: Children's Play Area | V21: Online Scheduling | W21: Pet Friendly | X21: 7603539300 | AE21: https://www.toyotatirecenter.com/?uid=B7489FF2-BA9E-43EE-B85BD33E154B883D | AF21: 2022-04-11 | AG21: 2026-06-08 | AH21: No Issue Detected
A22: 04374 | B22: Antioch Toyota | C22: 122 | D22: 925-778-4800 | E22: 1831 Auto Center Drvie | F22: Antioch | G22: CA | H22: 94509 | I22: https://www.antiochtoyota.com | J22: 24-Hour Vehicle Drop Off;Advanced Diagnostics;Advanced Tune-Up Equip.;Children's Play Area;Complimentary Beverages;Online Scheduling;Car Wash;Parts Center;RAV4 EV Service;Toyota Tire Center | K22: https://www.antiochtoyota.com/schedule-service.htm | L22: Monday 7:00 am - 6:00 pm~Tuesday 7:00 am - 6:00 pm~Wednesday 7:00 am - 6:00 pm~Thursday 7:00 am - 6:00 pm~Friday 7:00 am - 6:00 pm~Saturday 7:30 am - 5:00 pm~ | M22: jcarter@antiochtoyota.com | N22: Jonathon Carter | O22: Jonathan Carter | P22: Service Manager | R22: 24-Hour Vehicle Drop Off | S22: Advanced Diagnostics | T22: Advanced Tune-Up Equip. | U22: Children's Play Area | V22: Complimentary Beverages | W22: Online Scheduling | X22: 9257784800 | Y22: https://www.facebook.com/AntiochToyota | Z22: https://twitter.com/AntiochToyota | AA22: https://www.youtube.com/channel/UCE57cVv67XChxYom2SJxO2Q/about | AB22: https://www.yelp.com/biz/antioch-toyota-antioch | AE22: https://www.toyotatirecenter.com/?uid=7E531E1F-A184-446D-8378DEB9920E69D3 | AF22: 2022-04-11 | AG22: 2025-10-31 | AH22: Redirect Drops Query String | AI22: https://www.antiochtoyota.com/schedule-service.htm -> https://www.antiochtoyota.com/service/schedule-service/ (redirect drops query strings; confirmed by appending test params: https://www.antiochtoyota.com/schedule-service.htm?siteid=test&utm_source=test -> https://www.antiochtoyota.com/service/schedule-service/)
A23: 04454 | B23: Magnussen's Toyota of Palo Alto | C23: 121 | D23: 650-813-6121 | E23: 690 San Antonio Road | F23: Palo Alto | G23: CA | H23: 94306 | I23: https://www.toyotapaloalto.com | J23: Advanced Diagnostics;Advanced Tune-Up Equip.;Complimentary Ride Share;Online Scheduling;Spanish Speaking;Toyota Cert. Technicians;Express Lube;On-Site Rental Vehicles;Parts Center;RAV4 EV Service;Toyota Tire Center | K23: https://www.toyotapaloalto.com/schedule-service.htm | L23: Monday 7:00 am - 6:00 pm~Tuesday 7:00 am - 6:00 pm~Wednesday 7:00 am - 6:00 pm~Thursday 7:00 am - 6:00 pm~Friday 7:00 am - 6:00 pm~Saturday 7:00 am - 6:00 pm~ | M23: service@toyotapaloalto.com | O23: John Hausler | P23: Service Director | R23: Advanced Diagnostics | S23: Advanced Tune-Up Equip. | T23: Complimentary Ride Share | U23: Online Scheduling | V23: Spanish Speaking | W23: Toyota Cert. Technicians | X23: 6504942100 | Y23: https://www.facebook.com/toyotapaloalto | Z23: https://twitter.com/ToyotaPaloAlto | AA23: https://www.youtube.com/user/ToyotaOfPaloAlto | AB23: https://www.yelp.com/biz/magnussens-toyota-of-palo-alto-palo-alto | AE23: https://www.toyotatirecenter.com/?uid=C1F555AE-0F3D-0E7B-C4BE08D182251481 | AF23: 2022-04-11 | AG23: 2026-06-24 | AH23: No Issue Detected
A24: 04649 | B24: Toyota of Glendale | C24: 113 | D24: 818-244-4196 | E24: 1260 South Brand Blvd. | F24: Glendale | G24: CA | H24: 91204 | I24: https://www.toyotaofglendale.com | J24: 24-Hour Vehicle Drop Off;Advanced Diagnostics;Advanced Tune-Up Equip.;Complimentary Beverages;Complimentary Ride Share;Contactless Service;Auto Detailing;Express Lube;Express Maintenance;Mirai Service;On-Site Rental Vehicles;Parts Center;Pres. Customer 1st Award | K24: https://www.toyotaofglendale.com/toyota-schedule-service.htm | L24: Monday 7:00 am - 7:00 pm~Tuesday 7:00 am - 7:00 pm~Wednesday 7:00 am - 7:00 pm~Thursday 7:00 am - 7:00 pm~Friday 7:00 am - 7:00 pm~Saturday 8:00 am - 5:00 pm~ | M24: kris_toyotaofglendale@yahoo.com | O24: Robert Barahona | P24: Service Director | R24: 24-Hour Vehicle Drop Off | S24: Advanced Diagnostics | T24: Advanced Tune-Up Equip. | U24: Complimentary Beverages | V24: Complimentary Ride Share | W24: Contactless Service | X24: 8182444196 | Y24: https://www.facebook.com/glendaletoyota | Z24: https://twitter.com/glendaletoyota | AA24: https://www.youtube.com/channel/UC7dv0PKeSYT4d0JtBRSbYnQ | AB24: https://www.yelp.com/biz/oyota-of-glendale-glendale | AE24: https://www.toyotatirecenter.com/?uid=803E1BAD-2A46-4B50-9764661C41FA5136 | AF24: 2022-04-11 | AG24: 2026-06-08 | AH24: Redirect Drops Query String | AI24: https://www.toyotaofglendale.com/toyota-schedule-service.htm -> https://www.toyotaofglendale.com/service/schedule-service/ (redirect drops query strings; confirmed by appending test params: https://www.toyotaofglendale.com/toyota-schedule-service.htm?siteid=test&utm_source=test -> https://www.toyotaofglendale.com/service/schedule-service/)
A25: 04819 | B25: Temecula Valley Toyota | C25: 117 | D25: 951-695-0575 | E25: 26631 Ynez Road | F25: Temecula | G25: CA | H25: 92591 | I25: https://www.tvtoyota.com | J25: 24-Hour Vehicle Drop Off;Advanced Diagnostics;Advanced Tune-Up Equip.;Barista/Coffee Bar;Complimentary Beverages;Online Scheduling;Express Lube;Express Maintenance;Toyota Tire Center;Board of Governors Award;Pres. Customer 1st Award | K25: https://www.tvtoyota.com/schedule-service-appt.htm | L25: Monday 6:00 am - 5:00 pm~Tuesday 6:00 am - 5:00 pm~Wednesday 6:00 am - 5:00 pm~Thursday 6:00 am - 5:00 pm~Friday 6:00 am - 5:00 pm~Saturday 6:00 am - 5:00 pm~ | O25: Patrick Smith | P25: Service Manager | R25: 24-Hour Vehicle Drop Off | S25: Advanced Diagnostics | T25: Advanced Tune-Up Equip. | U25: Barista/Coffee Bar | V25: Complimentary Beverages | W25: Online Scheduling | X25: 9516940575 | Y25: https://www.facebook.com/toyotatemecula | Z25: https://twitter.com/tv_toyota | AA25: https://www.youtube.com/user/toyotaoftemecula | AB25: https://www.yelp.com/biz/temecula-valley-toyota-temecula-2 | AE25: https://www.toyotatirecenter.com/?uid=6C340654-A256-4F14-AE297D4C277E12C6 | AF25: 2022-04-11 | AG25: 2026-05-06 | AH25: Redirect Drops Query String | AI25: https://www.tvtoyota.com/schedule-service-appt.htm -> https://www.tvtoyota.com/schedule-service-online/ (redirect drops query strings; confirmed by appending test params: https://www.tvtoyota.com/schedule-service-appt.htm?siteid=test&utm_source=test -> https://www.tvtoyota.com/schedule-service-online/)
A26: 05071 | B26: McDonald Toyota | C26: 157 | D26: 970-339-3900 | E26: 4732 West 26th Street | F26: Greeley | G26: CO | H26: 80634 | I26: https://www.mcdonaldtoyotagreeley.com | J26: 24-Hour Vehicle Drop Off;Advanced Diagnostics;Advanced Tune-Up Equip.;Barista/Coffee Bar;Children's Play Area;Complimentary Beverages;Car Wash;Express Lube;Parts Center;RAV4 EV Service;Toyota Tire Center | K26: https://www.mcdonaldtoyotagreeley.com/schedule-service | L26: Monday 7:30 am - 6:00 pm~Tuesday 7:30 am - 6:00 pm~Wednesday 7:30 am - 6:00 pm~Thursday 7:30 am - 6:00 pm~Friday 7:30 am - 6:00 pm~Saturday 8:00 am - 4:00 pm~ | O26: Your Service Center | R26: 24-Hour Vehicle Drop Off | S26: Advanced Diagnostics | T26: Advanced Tune-Up Equip. | U26: Barista/Coffee Bar | V26: Children's Play Area | W26: Complimentary Beverages | X26: 9703393900 | AE26: https://www.toyotatirecenter.com/?uid=F4099638-031A-5E8A-EA1EF55293E1C3CB | AF26: 2022-04-11 | AG26: 2026-07-07 | AH26: No Issue Detected
A27: 06036 | B27: Middletown Toyota | C27: 164 | D27: 860-347-7294 | E27: 634 Newfield Street | F27: Middletown | G27: CT | H27: 06457 | I27: https://www.middletowntoyota.com | J27: 24-Hour Vehicle Drop Off;Advanced Diagnostics;Advanced Tune-Up Equip.;Barista/Coffee Bar;Late Pickup;Online Scheduling;Auto Detailing;Car Wash;On-Site Rental Vehicles;Parts Center;RAV4 EV Service;Toyota Tire Center;Pres. Customer 1st Award | K27: https://www.middletowntoyota.com/schedule-service | L27: Monday 7:00 am - 6:00 pm~Tuesday 7:00 am - 6:00 pm~Wednesday 7:00 am - 6:00 pm~Thursday 7:00 am - 6:00 pm~Friday 7:00 am - 6:00 pm~Saturday 7:00 am - 2:00 pm~ | M27: service@middletowntoyota.com | O27: Your Service Professionals | P27: Middletown Toyota | R27: 24-Hour Vehicle Drop Off | S27: Advanced Diagnostics | T27: Advanced Tune-Up Equip. | U27: Barista/Coffee Bar | V27: Late Pickup | W27: Online Scheduling | X27: 8603477294 | Y27: https://www.facebook.com/MiddletownToyota | Z27: https://twitter.com/middtoyota | AA27: https://www.youtube.com/user/Middletowntoyota1975 | AB27: https://www.yelp.com/biz/middletown-toyota-middletown | AC27: https://www.instagram.com/middletowntoyota/ | AF27: 2022-04-11 | AG27: 2026-05-06 | AH27: Unreachable / Timeout | AI27: ('Connection aborted.', RemoteDisconnected('Remote end closed connection without response')) | browser fallback unavailable: Page.goto: Timeout 20000ms exceeded. Call log: - navigating to "https://w
A28: 06037 | B28: Charles Toyota | C28: 164 | D28: 860-889-8375 | E28: 500 West Thames Street | F28: Norwich | G28: CT | H28: 06360 | I28: https://www.charlestoyota.com | J28: 24-Hour Vehicle Drop Off;Advanced Diagnostics;Advanced Tune-Up Equip.;Barista/Coffee Bar;Complimentary Beverages;Contactless Service;Express Lube;Parts Center;Toyota Collision Center;Toyota Tire Center | K28: https://www.charlestoyota.com/#modal-scheduleservice | L28: Monday 7:30 am - 5:00 pm~Tuesday 7:30 am - 5:00 pm~Wednesday 7:30 am - 5:00 pm~Thursday 7:30 am - 5:00 pm~Friday 7:30 am - 5:00 pm~Saturday 7:30 am - 12:30 pm~ | M28: service@charlestoyota.com | O28: Your Service Professionals | P28: Service Director | R28: 24-Hour Vehicle Drop Off | S28: Advanced Diagnostics | T28: Advanced Tune-Up Equip. | U28: Barista/Coffee Bar | V28: Complimentary Beverages | W28: Contactless Service | X28: 8608898375 | Y28: https://www.facebook.com/Charles.ToyotaCT/ | Z28: https://twitter.com/Charles_Toyota | AA28: https://www.youtube.com/user/charlestoyota | AB28: https://www.yelp.com/biz/charles-toyota-norwich-2 | AE28: https://www.toyotatirecenter.com/?uid=016A42E5-BE66-1FA4-F54572CBE472B43C | AF28: 2022-04-11 | AG28: 2026-05-06 | AH28: Same as Dealer_URL (homepage) | AK28: Low (candidates found but none loaded cleanly)
A29: 06042 | B29: Hoffman Toyota | C29: 164 | D29: 860-651-0207 | E29: 36 Albany Turnpike Rt 44 | F29: West Simsbury | G29: CT | H29: 06092 | I29: https://www.hoffmantoyota.com | J29: 24-Hour Vehicle Drop Off;Advanced Diagnostics;Advanced Tune-Up Equip.;Barista/Coffee Bar;Collision Loaner Vehicle;Complimentary Beverages;Auto Detailing;Parts Center;RAV4 EV Service;Toyota Collision Center;Toyota Tire Center;Pres. Customer 1st Award | K29: https://www.hoffmantoyota.com/Service_Toyota_Appt.htm | L29: Monday 7:00 am - 5:30 pm~Tuesday 7:00 am - 5:30 pm~Wednesday 7:00 am - 5:30 pm~Thursday 7:00 am - 5:30 pm~Friday 7:00 am - 5:30 pm~Saturday 7:30 am - 3:30 pm~ | M29: toyotaservice@hoffmanauto.com | O29: Mike Fitzgerald | P29: Service Manager | R29: 24-Hour Vehicle Drop Off | S29: Advanced Diagnostics | T29: Advanced Tune-Up Equip. | U29: Barista/Coffee Bar | V29: Collision Loaner Vehicle | W29: Complimentary Beverages | X29: 8606513725 | Y29: https://www.facebook.com/hoffmantoyota | Z29: https://twitter.com/HoffmanToyota | AA29: https://www.youtube.com/channel/UC2x_AcVG3AT5JPvxN6CWl7Q | AB29: https://www.yelp.com/biz/hoffman-toyota-west-simsbury | AC29: https://instagram.com/hoffmantoyota | AE29: https://www.toyotatirecenter.com/?uid=F1176E64-C03C-4166-8BB44C7543408EE0 | AF29: 2022-04-11 | AG29: 2024-07-25 | AH29: No Issue Detected
A30: 24026 | B30: Adams Toyota Lee's Summit | C30: 231 | D30: 816-358-7600 | E30: 501 N.E. Colbern Road | F30: Lee's Summit | G30: MO | H30: 64086 | I30: https://www.adamstoyota.com | J30: 24-Hour Vehicle Drop Off;Advanced Diagnostics;Advanced Tune-Up Equip.;Barista/Coffee Bar;Complimentary Beverages;Online Scheduling;Car Wash;Parts Center;Toyota Collision Center;Toyota Tire Center | K30: https://www.adamstoyota.com/service-appointment/ | L30: Monday 7:00 am - 6:00 pm~Tuesday 7:00 am - 6:00 pm~Wednesday 7:00 am - 6:00 pm~Thursday 7:00 am - 6:00 pm~Friday 7:00 am - 6:00 pm~Saturday 7:00 am - 4:00 pm~ | M30: ssweeney@adamsautogroup.com | O30: Shawn Sweeney | P30: Service Manager | R30: 24-Hour Vehicle Drop Off | S30: Advanced Diagnostics | T30: Advanced Tune-Up Equip. | U30: Barista/Coffee Bar | V30: Complimentary Beverages | W30: Online Scheduling | X30: 8163587600 | Y30: https://www.facebook.com/Adams-Toyota-Scion-74439592341 | Z30: https://twitter.com/AdamsToyota1 | AA30: https://www.youtube.com/channel/UCNLpE8xTQTBrkd0ddZulSug/videos | AB30: https://www.yelp.com/biz/adams-toyota-lees-summit | AE30: https://www.toyotatirecenter.com/?uid=0C22F017-0AEF-034F-6B7AAED9AAD6E042 | AF30: 2022-04-11 | AG30: 2025-09-16 | AH30: Error Page Entered | AI30: Status 403 at https://www.adamstoyota.com/service-appointment/ | AK30: None (no sitemap found; homepage links yielded no candidates)
A31: 24059 | B31: Baldwin Toyota | C31: 233 | D31: 573-785-6484 | E31: 801 S. Westwood Blvd. | F31: Poplar Bluff | G31: MO | H31: 63901 | I31: https://www.baldwintoyota.com | J31: 24-Hour Vehicle Drop Off;Advanced Diagnostics;Advanced Tune-Up Equip.;Barista/Coffee Bar;Complimentary Beverages;Contactless Service;Car Wash;Mirai Service;On-Site Rental Vehicles;Parts Center;RAV4 EV Service;State Cert. Inspection;Pres. Customer 1st Award | K31: https://www.baldwintoyota.com/service-appointment/ | L31: Monday 7:30 am - 5:00 pm~Tuesday 7:30 am - 5:00 pm~Wednesday 7:30 am - 5:00 pm~Thursday 7:30 am - 5:00 pm~Friday 7:30 am - 5:00 pm~Saturday 8:00 am - 12:00 pm~ | O31: David Allen | P31: Service Manager | R31: 24-Hour Vehicle Drop Off | S31: Advanced Diagnostics | T31: Advanced Tune-Up Equip. | U31: Barista/Coffee Bar | V31: Complimentary Beverages | W31: Contactless Service | X31: 5737856484 | Y31: https://www.facebook.com/baldwintoyota/timeline | Z31: https://twitter.com/BaldwinToyota | AA31: https://www.youtube.com/channel/UC22W4lViANRgQsbpK0f9ojQ | AB31: https://www.yelp.com/biz/baldwin-toyota-poplar-bluff-2 | AE31: https://www.toyotatirecenter.com/?uid=2E28ACBA-AFCA-4395-9E57E17B3E0ED341 | AF31: 2022-04-11 | AG31: 2026-05-06 | AH31: Error Page Entered | AI31: Status 403 at https://www.baldwintoyota.com/service-appointment/ | AK31: None (no sitemap found; homepage links yielded no candidates)
A32: 24071 | B32: Reliable Toyota | C32: 233 | D32: 833-685-4262 | E32: 3521 East Sunshine | F32: Springfield | G32: MO | H32: 65809 | I32: https://www.reliabletoyotamo.com | J32: 24-Hour Vehicle Drop Off;Advanced Diagnostics;Advanced Tune-Up Equip.;Barista/Coffee Bar;Children's Play Area;Complimentary Beverages;Auto Detailing;Car Wash;Express Lube;Express Maintenance;On-Site Rental Vehicles;Parts Center;Board of Governors Award | K32: https://www.reliabletoyotamo.com/service/appointment-form.htm | L32: Monday 7:30 am - 5:30 pm~Tuesday 7:30 am - 5:30 pm~Wednesday 7:30 am - 5:30 pm~Thursday 7:30 am - 5:30 pm~Friday 7:30 am - 5:30 pm~Saturday 8:00 am - 5:00 pm~ | M32: internetsales@reliablesuperstore.com | R32: 24-Hour Vehicle Drop Off | S32: Advanced Diagnostics | T32: Advanced Tune-Up Equip. | U32: Barista/Coffee Bar | V32: Children's Play Area | W32: Complimentary Beverages | X32: 4178899000 | Y32: https://www.facebook.com/reliabletoyota | Z32: https://twitter.com/ToyotaofSPD | AA32: https://www.youtube.com/user/ReliableSuperstore/about | AB32: https://www.yelp.com/biz/reliable-toyota-springfield | AE32: https://www.toyotatirecenter.com/?uid=E71F366A-9F82-69EC-97FD978938141ACA | AF32: 2022-04-11 | AG32: 2026-05-06 | AH32: No Issue Detected
A33: 25056 | B33: City Toyota | C33: 137 | D33: 406-761-4900 | E33: 3900 10th Avenue South | F33: Great Falls | G33: MT | H33: 59405 | I33: https://www.city-toyota.com | J33: 24-Hour Vehicle Drop Off;Advanced Diagnostics;Advanced Tune-Up Equip.;Barista/Coffee Bar;Complimentary Snacks;Contactless Service;Auto Detailing;Car Wash;Express Lube;Express Maintenance;Parts Center;Toyota Collision Center | K33: https://www.city-toyota.com/service-appointment/ | L33: Monday 7:30 am - 6:00 pm~Tuesday 7:30 am - 6:00 pm~Wednesday 7:30 am - 6:00 pm~Thursday 7:30 am - 6:00 pm~Friday 7:30 am - 6:00 pm~~ | O33: Service Manager | R33: 24-Hour Vehicle Drop Off | S33: Advanced Diagnostics | T33: Advanced Tune-Up Equip. | U33: Barista/Coffee Bar | V33: Complimentary Snacks | W33: Contactless Service | X33: 4067614900 | Y33: https://www.facebook.com/City-Toyota-285174657657 | Z33: https://twitter.com/citytoyotamt | AA33: https://www.youtube.com/channel/UC84VeMszhAJCwOKftkrZI6Q | AB33: https://www.yelp.com/biz/city-toyota-great-falls | AE33: https://www.toyotatirecenter.com/?uid=40EF38F1-2D04-4953-95A26FDCB698FC96 | AF33: 2022-04-11 | AG33: 2026-02-02 | AH33: No Issue Detected
A34: 25060 | B34: Toyota of Bozeman | C34: 137 | D34: 406-585-2002 | E34: 8476 Huffine Lane | F34: Bozeman | G34: MT | H34: 59718 | I34: https://www.toyotaofbozeman.com | J34: 24-Hour Vehicle Drop Off;Advanced Diagnostics;Advanced Tune-Up Equip.;Complimentary Beverages;Contactless Service;Online Scheduling;Auto Detailing;Car Wash;Express Lube;Express Maintenance;On-Site Rental Vehicles;Parts Center;Pres. Customer 1st Award | K34: https://www.toyotaofbozeman.com/?schedule=true | L34: Monday 7:30 am - 6:00 pm~Tuesday 7:30 am - 6:00 pm~Wednesday 7:30 am - 6:00 pm~Thursday 7:30 am - 6:00 pm~Friday 7:30 am - 6:00 pm~Saturday 8:00 am - 5:00 pm~ | M34: cparsch@resslermotors.com | R34: 24-Hour Vehicle Drop Off | S34: Advanced Diagnostics | T34: Advanced Tune-Up Equip. | U34: Complimentary Beverages | V34: Contactless Service | W34: Online Scheduling | X34: 4065852002 | Y34: https://www.facebook.com/bozemantoyota/timeline | Z34: https://twitter.com/toyotaofbozeman | AA34: https://www.youtube.com/channel/UCKEQ7KmWCdRtVI5b9DSDAaw | AB34: https://www.yelp.com/biz/toyota-of-bozeman-bozeman | AF34: 2022-04-11 | AG34: 2026-06-08 | AH34: Same as Dealer_URL (homepage) | AJ34: https://www.toyotaofbozeman.com/vehicle-finder-service/ | AK34: High
A35: 25068 | B35: Toyota of Helena | C35: 137 | D35: 406-430-6904 | E35: 3365 Highway 12 East | F35: Helena | G35: MT | H35: 59601 | I35: https://www.toyotaofhelena.com | J35: 24-Hour Vehicle Drop Off;Advanced Diagnostics;Complimentary Beverages;Complimentary Snacks;Online Scheduling;Pet Friendly;On-Site Rental Vehicles;Parts Center | K35: https://www.toyotaofhelena.com/service/ | L35: Monday 7:00 am - 6:00 pm~Tuesday 7:00 am - 6:00 pm~Wednesday 7:00 am - 6:00 pm~Thursday 7:00 am - 6:00 pm~Friday 7:00 am - 6:00 pm~Saturday 7:00 am - 5:00 pm~ | M35: HMITTON@HELENATOYOTA.COM | N35: Horald Mitton | O35: Your "No Problem" Dealership | R35: 24-Hour Vehicle Drop Off | S35: Advanced Diagnostics | T35: Complimentary Beverages | U35: Complimentary Snacks | V35: Online Scheduling | W35: Pet Friendly | X35: 4064426310 | Y35: https://www.facebook.com/helenatoyota | AA35: https://www.youtube.com/@ToyotaOfHelena | AB35: https://www.yelp.com/biz/toyota-of-helena-helena | AD35: https://www.toyotaofhelena.com/new-vehicles/ | AE35: https://www.toyotatirecenter.com/?uid=83A13E3F-99AF-FF2C-94EA0B142255C951 | AF35: 2022-08-02 | AG35: 2026-06-08 | AH35: No Issue Detected
A36: 26024 | B36: Baxter Toyota of Lincoln | C36: 235 | D36: 402-476-4001 | E36: 8600 South 33rd Street | F36: Lincoln | G36: NE | H36: 68516 | I36: https://www.toyotaoflincoln.com | J36: 24-Hour Vehicle Drop Off;Advanced Diagnostics;Advanced Tune-Up Equip.;Barista/Coffee Bar;Complimentary Beverages;Online Scheduling;Auto Detailing;Express Lube;Express Maintenance;Parts Center;Toyota Tire Center;Pres. Customer 1st Award | K36: https://www.toyotaoflincoln.com/service/schedule-service/ | L36: Monday 6:00 am - 6:00 pm~Tuesday 6:00 am - 6:00 pm~Wednesday 6:00 am - 6:00 pm~Thursday 6:00 am - 6:00 pm~Friday 6:00 am - 6:00 pm~Saturday 6:00 am - 3:00 pm~ | M36: service@performancetoyotaoflincoln.com | N36: Matt Quimby | O36: Matt Quimby | P36: Service Manager | R36: 24-Hour Vehicle Drop Off | S36: Advanced Diagnostics | T36: Advanced Tune-Up Equip. | U36: Barista/Coffee Bar | V36: Complimentary Beverages | W36: Online Scheduling | X36: 4024764000 | Y36: https://www.facebook.com/BaxterToyotaLincoln | Z36: https://twitter.com/toyotalincoln | AA36: https://www.youtube.com/channel/UCrdSakUdSrqXbd8_9WocAhA | AB36: https://www.yelp.com/biz/performance-toyota-scion-of-lincoln-lincoln | AF36: 2022-04-11 | AG36: 2026-06-08 | AH36: No Issue Detected
A37: 39040 | B37: Stokes Toyota Beaufort | C37: 50G | D37: 843-522-3232 | E37: 3557 Trask Parkway | F37: Beaufort | G37: SC | H37: 29906 | I37: https://www.stokestoyotabeaufort.com | J37: Spanish Speaking;Toyota Tire Center | K37: https://www.stokestoyotabeaufort.com/service/schedule-service/ | L37: Monday 7:30 am - 6:00 pm~Tuesday 7:30 am - 6:00 pm~Wednesday 7:30 am - 6:00 pm~Thursday 7:30 am - 6:00 pm~Friday 7:30 am - 6:00 pm~Saturday 7:30 am - 4:00 pm~ | R37: Spanish Speaking | X37: 8435223232 | Y37: https://www.facebook.com/stokesbrowntoyotabft | Z37: https://twitter.com/StokesBrown | AA37: https://www.youtube.com/user/stokesbrowntoyotab | AB37: https://www.yelp.com/biz/stokes-brown-toyota-scion-beaufort | AC37: https://www.instagram.com/stokesbrowntoyotab | AE37: https://www.settirecenters.com/?uid=DBA9A759-70F8-43F9-B223BC18897A76CF | AF37: 2022-04-11 | AG37: 2026-05-06 | AH37: No Issue Detected
A38: 41043 | B38: Principle Toyota | C38: 228 | D38: 901-758-4040 | E38: 7370 Winchester Road | F38: Memphis | G38: TN | H38: 38125 | I38: https://www.principletoyota.com | J38: 24-Hour Vehicle Drop Off;Advanced Diagnostics;Advanced Tune-Up Equip.;Barista/Coffee Bar;Child Car Seat Check;Children's Play Area;Auto Detailing;Express Lube;On-Site Rental Vehicles;Parts Center;Toyota Tire Center | K38: https://www.principletoyota.com/service-scheduler.htm | L38: Monday 7:00 am - 6:00 pm~Tuesday 7:00 am - 6:00 pm~Wednesday 7:00 am - 6:00 pm~Thursday 7:00 am - 6:00 pm~Friday 7:00 am - 6:00 pm~Saturday 7:00 am - 5:00 pm~ | M38: dmontgomery@principleautomotive.com | O38: David Montgomery | P38: Service Director | R38: 24-Hour Vehicle Drop Off | S38: Advanced Diagnostics | T38: Advanced Tune-Up Equip. | U38: Barista/Coffee Bar | V38: Child Car Seat Check | W38: Children's Play Area | X38: 9017584040 | Y38: https://www.facebook.com/principletoyotaofmemphis | Z38: https://twitter.com/PrincipleToyota | AA38: https://www.youtube.com/channel/UCVF6qdfibXUTzyJEx-0zw3g | AB38: https://www.yelp.com/biz/principle-toyota-memphis-2 | AE38: https://www.toyotatirecenter.com/?uid=98B71AE5-FC6A-F31E-3739725B11A28648 | AF38: 2022-04-11 | AG38: 2026-02-20 | AH38: No Issue Detected
A39: 41056 | B39: Toyota of Cleveland | C39: 2210 | D39: 423-339-1138 | E39: 3560 Village North Bl SW | F39: McDonald | G39: TN | H39: 37353 | I39: https://www.toyotaofcleveland.com | J39: 24-Hour Vehicle Drop Off;Advanced Diagnostics;Advanced Tune-Up Equip.;Barista/Coffee Bar;Children's Play Area;Complimentary Beverages;Auto Detailing;Car Wash;Express Lube;Express Maintenance;Parts Center;Toyota Tire Center;Pres. Customer 1st Award | K39: https://www.toyotaofcleveland.com/service/scheduler.htm | L39: Monday 7:00 am - 6:00 pm~Tuesday 7:00 am - 6:00 pm~Wednesday 7:00 am - 6:00 pm~Thursday 7:00 am - 6:00 pm~Friday 7:00 am - 6:00 pm~Saturday 8:00 am - 4:00 pm~ | M39: tomtrout@toyotaofcleveland.com | R39: 24-Hour Vehicle Drop Off | S39: Advanced Diagnostics | T39: Advanced Tune-Up Equip. | U39: Barista/Coffee Bar | V39: Children's Play Area | W39: Complimentary Beverages | X39: 4233391138 | Y39: https://www.facebook.com/ToyotaofCleveland | Z39: https://twitter.com/toyotafun | AA39: https://www.youtube.com/channel/UC7Y7wTx0G8OjQw25k7dtXFw | AB39: https://www.yelp.com/biz/toyota-of-cleveland-mc-donald | AC39: https://www.instagram.com/toyota.of.cleveland/?hl=en | AE39: https://www.toyotatirecenter.com/?uid=AFF72729-FE4B-3BD1-60CE9153432DDD99 | AF39: 2022-04-11 | AG39: 2026-06-08 | AH39: No Issue Detected
A40: 41061 | B40: Rick McGill's Airport Toyota | C40: 2210 | D40: 888-213-4062 | E40: 3145 Alcoa Highway | F40: Alcoa | G40: TN | H40: 37701 | I40: https://www.rickmcgillairporttoyota.com | J40: 24-Hour Vehicle Drop Off;Advanced Diagnostics;Advanced Tune-Up Equip.;Barista/Coffee Bar;Complimentary Beverages;Complimentary Snacks;Auto Detailing;Express Maintenance;On-Site Rental Vehicles;Parts Center;Toyota Tire Center | K40: https://www.rickmcgillairporttoyota.com/ | L40: Monday 7:00 am - 6:00 pm~Tuesday 7:00 am - 6:00 pm~Wednesday 7:00 am - 6:00 pm~Thursday 7:00 am - 6:00 pm~Friday 7:00 am - 6:00 pm~Saturday 7:30 am - 4:00 pm~ | M40: sales@rickmcgillsairporttoyota.edealerhub.com | N40: Gary Sergent | O40: Rick Mcgill | P40: President | R40: 24-Hour Vehicle Drop Off | S40: Advanced Diagnostics | T40: Advanced Tune-Up Equip. | U40: Barista/Coffee Bar | V40: Complimentary Beverages | W40: Complimentary Snacks | X40: 8659702615 | Y40: https://www.facebook.com/RickMcGillsAirportToyotaScion | Z40: https://twitter.com/mcgilltoyota | AA40: https://www.youtube.com/@rickmcgillairporttoyota | AB40: https://www.yelp.com/biz/mcgills-rick-airport-toyota-alcoa | AD40: https://www.rickmcgillairporttoyota.com/toyota-alcoa-tn.html | AE40: https://www.toyotatirecenter.com/?uid=2A16900D-0AA3-A0F8-34F9EBD358A0E62E | AF40: 2022-04-11 | AG40: 2026-05-06 | AH40: Same as Dealer_URL (homepage) | AJ40: https://www.rickmcgillairporttoyota.com/toyota-schedule-service.htm | AK40: High
A41: 41079 | B41: Toyota of Murfreesboro | C41: 229 | D41: 615-849-1620 | E41: 3434 Bill Smith Drive | F41: Murfreesboro | G41: TN | H41: 37129 | I41: https://www.toyotaofmurfreesboro.com | J41: 24-Hour Vehicle Drop Off;Advanced Diagnostics;Advanced Tune-Up Equip.;Barista/Coffee Bar;Contactless Service;Online Scheduling;Car Wash;Express Lube;Express Maintenance;On-Site Rental Vehicles;Parts Center;Toyota Collision Center | K41: https://www.toyotaofmurfreesboro.com/service-appointment/ | L41: Monday 7:00 am - 6:00 pm~Tuesday 7:00 am - 6:00 pm~Wednesday 7:00 am - 6:00 pm~Thursday 7:00 am - 6:00 pm~Friday 7:00 am - 6:00 pm~Saturday 7:00 am - 5:00 pm~ | M41: mthomas@toyotaofmurfreesboro.com | O41: Mike Thomas | P41: Service Director | R41: 24-Hour Vehicle Drop Off | S41: Advanced Diagnostics | T41: Advanced Tune-Up Equip. | U41: Barista/Coffee Bar | V41: Contactless Service | W41: Online Scheduling | X41: 6158901500 | Y41: https://www.facebook.com/toyotascionofmurfreesboro | Z41: https://twitter.com/murfreesborotoy | AA41: https://www.youtube.com/user/toyotaofmurfreesboro | AB41: https://www.yelp.com/biz/toyota-of-murfreesboro-murfreesboro-2 | AE41: https://www.toyotatirecenter.com/?uid=FDE1735F-A9EE-5026-5E0264EEAFF5E18E | AF41: 2022-04-11 | AG41: 2026-05-06 | AH41: Error Page Entered | AI41: Status 403 at https://www.toyotaofmurfreesboro.com/service-appointment/ | AK41: None (no sitemap found; homepage links yielded no candidates)
A42: 41085 | B42: Beaman Toyota | C42: 229 | D42: 629-243-3175 | E42: 343 Harding Place | F42: Nashville | G42: TN | H42: 37211 | I42: https://www.beamantoyota.com | J42: 24-Hour Vehicle Drop Off;Advanced Diagnostics;Advanced Tune-Up Equip.;Barista/Coffee Bar;Complimentary Beverages;Complimentary Ride Share;Auto Detailing;Car Wash;Express Lube;Express Maintenance;On-Site Rental Vehicles;Parts Center;LEED Certified Facility | K42: https://www.beamantoyota.com/service-center-schedule-service/ | L42: Monday 6:00 am - 7:00 pm~Tuesday 6:00 am - 7:00 pm~Wednesday 6:00 am - 7:00 pm~Thursday 6:00 am - 7:00 pm~Friday 6:00 am - 7:00 pm~Saturday 6:00 am - 4:00 pm~ | R42: 24-Hour Vehicle Drop Off | S42: Advanced Diagnostics | T42: Advanced Tune-Up Equip. | U42: Barista/Coffee Bar | V42: Complimentary Beverages | W42: Complimentary Ride Share | X42: 6152518400 | AE42: https://www.toyotatirecenter.com/?uid=D5B53583-C4FB-A1D9-B1A838C5BF278DD3 | AF42: 2022-04-11 | AG42: 2026-05-15 | AH42: Redirect Drops Query String | AI42: https://www.beamantoyota.com/service-center-schedule-service/ -> https://www.beamantoyota.com/service/schedule-service/ (redirect drops query strings; confirmed by appending test params: https://www.beamantoyota.com/service-center-schedule-service/?siteid=test&utm_source=test -> https://www.beamantoyota.com/service/schedule-service/)
A43: 41087 | B43: Toyota of Bristol | C43: 2210 | D43: 423-764-3155 | E43: 3045 W. State Street | F43: Bristol | G43: TN | H43: 37620 | I43: https://www.toyotaofbristol.com | J43: 24-Hour Vehicle Drop Off;Advanced Diagnostics;Advanced Tune-Up Equip.;Barista/Coffee Bar;Children's Play Area;Complimentary Beverages;Auto Detailing;Parts Center;Toyota Tire Center | K43: https://www.toyotaofbristol.com/service-center/schedule-express-service.htm | L43: Monday 7:30 am - 6:30 pm~Tuesday 7:30 am - 6:30 pm~Wednesday 7:30 am - 6:30 pm~Thursday 7:30 am - 6:30 pm~Friday 7:30 am - 6:30 pm~Saturday 8:00 am - 5:00 pm~ | R43: 24-Hour Vehicle Drop Off | S43: Advanced Diagnostics | T43: Advanced Tune-Up Equip. | U43: Barista/Coffee Bar | V43: Children's Play Area | W43: Complimentary Beverages | X43: 4237643155 | AE43: https://www.toyotatirecenter.com/?uid=4A782B68-984E-4AC9-AB87F1C8621AED23 | AF43: 2022-04-11 | AG43: 2026-05-06 | AH43: No Issue Detected
A44: 12137 | B44: Classic Toyota | C44: 211 | D44: 847-336-4300 | E44: 515 N. Green Bay Road | F44: Waukegan | G44: IL | H44: 60085 | I44: https://www.classicdirecttoyota.com | J44: 24-Hour Vehicle Drop Off;Advanced Diagnostics;Advanced Tune-Up Equip.;Barista/Coffee Bar;Children's Play Area;Complimentary Beverages;Auto Detailing;Car Wash;On-Site Rental Vehicles;Parts Center;Toyota Tire Center;Pres. Customer 1st Award | K44: https://www.classicdirecttoyota.com/Schedule-service.html | L44: Monday 7:00 am - 6:00 pm~Tuesday 7:00 am - 6:00 pm~Wednesday 7:00 am - 6:00 pm~Thursday 7:00 am - 6:00 pm~Friday 7:00 am - 6:00 pm~Saturday 7:00 am - 4:00 pm~ | M44: service@classicdealergroup.com | O44: Bill King | P44: Parts and Service Director | R44: 24-Hour Vehicle Drop Off | S44: Advanced Diagnostics | T44: Advanced Tune-Up Equip. | U44: Barista/Coffee Bar | V44: Children's Play Area | W44: Complimentary Beverages | X44: 8473364300 | Y44: https://www.facebook.com/classicdealergroup | Z44: https://twitter.com/ClasToyota | AA44: https://www.youtube.com/channel/UCzegsPiVXelj_jeB-HXR_Ww | AB44: https://www.yelp.com/biz/classic-toyota-waukegan-3 | AE44: https://www.toyotatirecenter.com/?uid=92C647D9-C123-9DAD-EC495841904A0D00 | AF44: 2022-04-11 | AG44: 2026-05-06 | AH44: Redirect Drops Query String | AI44: https://www.classicdirecttoyota.com/Schedule-service.html -> https://www.classicdirecttoyota.com/#schedule-service (redirect drops query strings; confirmed by appending test params: https://www.classicdirecttoyota.com/Schedule-service.html?siteid=test&utm_source=test -> https://www.classicdirecttoyota.com/#schedule-service?siteid=test&utm_source=test)
A45: 12151 | B45: Brian Bemis Toyota of DeKalb | C45: 218 | D45: 815-748-7300 | E45: 1890 Sycamore Road | F45: DeKalb | G45: IL | H45: 60115 | I45: https://www.dekalbtoyota.com | J45: 24-Hour Vehicle Drop Off;Advanced Diagnostics;Advanced Tune-Up Equip.;Children's Play Area;Complimentary Beverages;Complimentary Snacks;Auto Detailing;Car Wash;Express Lube;Parts Center;Toyota Tire Center | L45: Monday 7:30 am - 5:30 pm~Tuesday 7:30 am - 5:30 pm~Wednesday 7:30 am - 5:30 pm~Thursday 7:30 am - 5:30 pm~Friday 7:30 am - 5:30 pm~Saturday 7:30 am - 4:00 pm~ | M45: jemerich@brianbemis.com | N45: Ken Olson | O45: Joe Emerich | P45: Service Director | R45: 24-Hour Vehicle Drop Off | S45: Advanced Diagnostics | T45: Advanced Tune-Up Equip. | U45: Children's Play Area | V45: Complimentary Beverages | W45: Complimentary Snacks | X45: 8157487300 | AE45: https://www.toyotatirecenter.com/?uid=DE2FB954-A5EF-B33F-E0DB633AEC2BC297 | AF45: 2022-04-11 | AG45: 2026-06-16 | AH45: No URL | AJ45: https://www.dekalbtoyota.com/service/toyota-maintenance-schedule/ | AK45: High
A46: 12159 | B46: Advantage Toyota of River Oaks | C46: 213 | D46: 708-862-0700 | E46: 1970 River Oaks Drive | F46: Calumet City | G46: IL | H46: 60409 | I46: https://www.advantagetoyotariveroaks.com | J46: 24-Hour Vehicle Drop Off;Advanced Diagnostics;Advanced Tune-Up Equip.;Barista/Coffee Bar;Contactless Service;Late Pickup;Car Wash;Express Lube;On-Site Rental Vehicles;Parts Center | K46: https://www.advantagetoyotariveroaks.com/#modal-scheduleservice | L46: Monday 7:00 am - 5:00 pm~Tuesday 7:00 am - 5:00 pm~Wednesday 7:00 am - 5:00 pm~Thursday 7:00 am - 5:00 pm~Friday 7:00 am - 5:00 pm~Saturday 7:00 am - 3:00 pm~ | O46: Tony Thiel | P46: Service Manager | R46: 24-Hour Vehicle Drop Off | S46: Advanced Diagnostics | T46: Advanced Tune-Up Equip. | U46: Barista/Coffee Bar | V46: Contactless Service | W46: Late Pickup | X46: 7088620700 | AE46: https://www.toyotatirecenter.com/?uid=C3FF7E3E-9773-A609-526A5A4721B586B5 | AF46: 2022-04-11 | AG46: 2026-05-06 | AH46: Same as Dealer_URL (homepage) | AK46: None (no sitemap found; homepage links yielded no candidates)
A47: 12162 | B47: Monken Toyota of Mt. Vernon | C47: 215 | D47: 618-242-0334 | E47: 100 South 45th Street | F47: Mt Vernon | G47: IL | H47: 62864 | I47: https://www.monkentoyotamtvernon.com | J47: 24-Hour Vehicle Drop Off;Advanced Diagnostics;Advanced Tune-Up Equip.;Barista/Coffee Bar;Complimentary Beverages;Contactless Service;Parts Center;RAV4 EV Service;Toyota Tire Center | K47: https://www.monkentoyotamtvernon.com/schedule-service.html | L47: Monday 8:00 am - 5:00 pm~Tuesday 8:00 am - 5:00 pm~Wednesday 8:00 am - 5:00 pm~Thursday 8:00 am - 5:00 pm~Friday 8:00 am - 5:00 pm~~ | R47: 24-Hour Vehicle Drop Off | S47: Advanced Diagnostics | T47: Advanced Tune-Up Equip. | U47: Barista/Coffee Bar | V47: Complimentary Beverages | W47: Contactless Service | X47: 6182420334 | Y47: https://www.facebook.com/Monkentoyota | AE47: https://www.toyotatirecenter.com/?uid=A1112BEC-F6E7-4F46-966AC82267AFBF46 | AF47: 2022-04-11 | AG47: 2026-06-08 | AH47: No Issue Detected
A48: 12168 | B48: Kunes Toyota of Galesburg | C48: 216 | D48: 309-344-2080 | E48: 2763 N. Seminary Street | F48: Galesburg | G48: IL | H48: 61401 | I48: https://www.kunesgalesburgtoyota.com | J48: 24-Hour Vehicle Drop Off;Advanced Diagnostics;Advanced Tune-Up Equip.;Barista/Coffee Bar;Complimentary Beverages;Complimentary Snacks;Auto Detailing;Express Lube;On-Site Rental Vehicles;Parts Center;Toyota Tire Center | K48: https://www.kunestoyota.com/scheduleservice.html | L48: Monday 7:30 am - 5:30 pm~Tuesday 7:30 am - 5:30 pm~Wednesday 7:30 am - 5:30 pm~Thursday 7:30 am - 5:30 pm~Friday 7:30 am - 5:30 pm~Saturday 8:00 am - 4:00 pm~ | R48: 24-Hour Vehicle Drop Off | S48: Advanced Diagnostics | T48: Advanced Tune-Up Equip. | U48: Barista/Coffee Bar | V48: Complimentary Beverages | W48: Complimentary Snacks | X48: 3093442080 | Y48: https://facebook.com/kunesgalesburg | AE48: https://www.toyotatirecenter.com/?uid=4C878B6B-A7EB-42F2-B9C2D42B52177512 | AF48: 2022-04-11 | AG48: 2024-01-18 | AH48: Different Domain (Unverified) | AI48: Hosted on kunestoyota.com, not on dealer's own domain (kunesgalesburgtoyota.com), but not on the known 3rd-party scheduler list -- verify manually
A49: 12173 | B49: Ottawa Toyota | C49: 216 | D49: 815-434-4000 | E49: 4000 N. Columbus Street | F49: Ottawa | G49: IL | H49: 61350 | I49: https://www.ottawatoyotadealer.com | J49: 24-Hour Vehicle Drop Off;Advanced Diagnostics;Advanced Tune-Up Equip.;Complimentary Beverages;Shuttle Service;Toyota Cert. Technicians;Car Wash | K49: https://www.ottawatoyotadealer.com/scheduleservice | L49: Monday 7:00 am - 6:00 pm~Tuesday 7:00 am - 6:00 pm~Wednesday 7:00 am - 6:00 pm~Thursday 7:00 am - 6:00 pm~Friday 7:00 am - 6:00 pm~Saturday 7:00 am - 3:00 pm~ | R49: 24-Hour Vehicle Drop Off | S49: Advanced Diagnostics | T49: Advanced Tune-Up Equip. | U49: Complimentary Beverages | V49: Shuttle Service | W49: Toyota Cert. Technicians | X49: 8154344000 | AE49: https://www.toyotatirecenter.com/?uid=CF47608F-BAAC-465D-AA1A264702543F51 | AF49: 2025-12-15 | AG49: 2026-06-11 | AH49: No Issue Detected
A50: 13060 | B50: Team Toyota | C50: 213 | D50: 219-924-8100 | E50: 400 Indianapolis Blvd. | F50: Schererville | G50: IN | H50: 46375 | I50: https://www.teamtoyotaon41.com | J50: Barista/Coffee Bar;Children's Play Area;Online Scheduling;Pet Friendly;Service Loaner Vehicle;Shuttle Service;Car Wash;On-Site Rental Vehicles;Parts Center;Toyota Tire Center | K50: https://www.teamtoyotaon41.com/service/schedule-service/ | L50: Monday 7:30 am - 6:00 pm~Tuesday 7:30 am - 6:00 pm~Wednesday 7:30 am - 6:00 pm~Thursday 7:30 am - 6:00 pm~Friday 7:30 am - 6:00 pm~Saturday 8:00 am - 4:00 pm~ | M50: leads@teamtoyotaon41.com | O50: Jason Akers | P50: General Manager | R50: Barista/Coffee Bar | S50: Children's Play Area | T50: Online Scheduling | U50: Pet Friendly | V50: Service Loaner Vehicle | W50: Shuttle Service | X50: 2199248100 | Y50: https://www.facebook.com/teamtoyotaon41/ | Z50: https://twitter.com/TeamToyotaon41 | AA50: https://www.youtube.com/user/teamtoyota1 | AB50: https://www.yelp.com/biz/team-toyota-schererville | AE50: https://www.toyotatirecenter.com/?uid=3FFD9B10-CCD4-81E7-C604BB368F920703 | AF50: 2022-04-11 | AG50: 2024-02-23 | AH50: Redirect Drops Query String | AI50: https://www.teamtoyotaon41.com/service/schedule-service/ -> https://www.teamtoyotaon41.com/scheduleservice (redirect drops query strings; confirmed by appending test params: https://www.teamtoyotaon41.com/service/schedule-service/?siteid=test&utm_source=test -> https://www.teamtoyotaon41.com/)
A51: 13076 | B51: Cronin Toyota of Richmond | C51: 214 | D51: 765-966-4569 | E51: 5601 National Road East | F51: Richmond | G51: IN | H51: 47374 | I51: https://www.cronintoyotaofrichmond.com | K51: https://www.cronintoyotaofrichmond.com/service-appointment/ | L51: Monday 7:30 am - 6:00 pm~Tuesday 7:30 am - 6:00 pm~Wednesday 7:30 am - 6:00 pm~Thursday 7:30 am - 6:00 pm~Friday 7:30 am - 6:00 pm~Saturday 8:00 am - 3:00 pm~ | O51: Robin Moore | P51: Service Manager | X51: 7659664569 | AE51: https://www.toyotatirecenter.com/?uid=54B2D6BD-9BAD-4601-A7916C8498909EA5 | AF51: 2022-04-11 | AG51: 2023-05-16 | AH51: Error Page Entered | AI51: Status 403 at https://www.cronintoyotaofrichmond.com/service-appointment/ | AK51: None (no sitemap found; homepage links yielded no candidates)
A52: 13077 | B52: Bill Estes Toyota | C52: 214 | D52: 317-846-9600 | E52: 3232 Harper Road | F52: Indianapolis | G52: IN | H52: 46240 | I52: https://www.billestestoyota.com | J52: Toyota Collision Center | K52: https://www.billestestoyota.com/service/schedule.htm | L52: Monday 7:30 am - 6:00 pm~Tuesday 7:30 am - 6:00 pm~Wednesday 7:30 am - 6:00 pm~Thursday 7:30 am - 6:00 pm~Friday 7:30 am - 5:30 pm~Saturday 8:00 am - 3:00 pm~ | O52: Mike Berry | P52: Service Director | X52: 3178469600 | AE52: https://www.toyotatirecenter.com/?uid=9200130A-F2C9-FE13-426DEA5C083E2C6C | AF52: 2022-04-11 | AG52: 2026-06-08 | AH52: No Issue Detected
A53: 13079 | B53: Toyota of Madison | C53: 214 | D53: 812-273-3135 | E53: 258 Clifty Drive | F53: Madison | G53: IN | H53: 47250 | I53: https://www.toyotaofmadison.net | J53: Express Maintenance | K53: https://www.toyotaofmadison.net/service-center.html | L53: Monday 8:00 am - 5:00 pm~Tuesday 8:00 am - 5:00 pm~Wednesday 8:00 am - 5:00 pm~Thursday 8:00 am - 5:00 pm~Friday 8:00 am - 5:00 pm~Saturday 8:00 am - 12:00 pm~ | X53: 8122733135 | Y53: https://www.facebook.com/ToyotaofMadison/ | AE53: https://www.toyotatirecenter.com/?uid=2C1640E0-E61F-13D0-66DF9DF1EAED1998 | AF53: 2024-08-01 | AG53: 2026-06-08 | AH53: No Issue Detected
A54: 45094 | B54: Gloucester Toyota | C54: 805 | D54: 804-693-2100 | E54: 6357 George Washington Highway | F54: Gloucester | G54: VA | H54: 23061 | I54: https://www.gloucestertoyota.com | J54: 24-Hour Vehicle Drop Off;Advanced Diagnostics;Advanced Tune-Up Equip.;Complimentary Beverages;EV Charging Station;Late Pickup;On-Site Rental Vehicles;Parts Center;State Cert. Inspection;Pres. Customer 1st Award | K54: https://www.gloucestertoyota.com/service/ | L54: Monday 7:30 am - 5:30 pm~Tuesday 7:30 am - 5:30 pm~Wednesday 7:30 am - 5:30 pm~Thursday 7:30 am - 5:30 pm~Friday 7:30 am - 5:30 pm~Saturday 8:00 am - 3:00 pm~ | M54: service@gloucestertoyota.com | N54: Doug Updike | O54: Jeff Brown | P54: Dealer Principal | R54: 24-Hour Vehicle Drop Off | S54: Advanced Diagnostics | T54: Advanced Tune-Up Equip. | U54: Complimentary Beverages | V54: EV Charging Station | W54: Late Pickup | X54: 8046932100 | Y54: https://www.facebook.com/gloucestertoy | Z54: https://twitter.com/GloucesterToy | AA54: https://www.youtube.com/@gloucester_toyota | AC54: https://www.instagram.com/gloucestertoyota1/ | AD54: https://www.gloucestertoyota.com/ | AE54: https://www.toyotatirecenter.com/?uid=A28AEA7E-E567-E5B8-806BDEF6A77756E9 | AF54: 2022-04-11 | AG54: 2026-02-25 | AH54: No Issue Detected
A55: 45095 | B55: Hall Toyota Virginia Beach | C55: 805 | D55: 757-767-4375 | E55: 1877 Laskin Road | F55: Virginia Beach | G55: VA | H55: 23454 | I55: https://www.halltoyotavirginiabeach.com | J55: 24-Hour Vehicle Drop Off;Complimentary Beverages;Online Scheduling;Pet Friendly;Pick Up/Delivery Options;Shuttle Service;Car Wash;Express Lube;Toyota Collision Center | K55: https://www.halltoyotavirginiabeach.com/service/service-scheduler.htm | L55: Monday 7:00 am - 6:00 pm~Tuesday 7:00 am - 6:00 pm~Wednesday 7:00 am - 6:00 pm~Thursday 7:00 am - 6:00 pm~Friday 7:00 am - 6:00 pm~Saturday 7:00 am - 3:00 pm~ | O55: Bill Baker | P55: President | R55: 24-Hour Vehicle Drop Off | S55: Complimentary Beverages | T55: Online Scheduling | U55: Pet Friendly | V55: Pick Up/Delivery Options | W55: Shuttle Service | X55: 7574374000 | Y55: https://www.facebook.com/HallToyotaVirginiaBeach | AC55: https://www.instagram.com/halltoyotavirginiabeach/ | AE55: https://www.toyotatirecenter.com/?uid=7B5358A9-D90F-146D-3661BF1890F13540 | AF55: 2022-04-11 | AG55: 2026-06-08 | AH55: No Issue Detected
A56: 45096 | B56: Toyota of Woodbridge | C56: 804 | D56: 703-492-3615 | E56: 14227 Richmond Highway | F56: Woodbridge | G56: VA | H56: 22191 | I56: https://www.toyotawoodbridge.com | J56: 24-Hour Vehicle Drop Off;Advanced Diagnostics;Advanced Tune-Up Equip.;Late Pickup;Pet Friendly;Shuttle Service;Car Wash;Express Lube;Express Maintenance;On-Site Rental Vehicles;State Cert. Inspection | K56: https://www.toyotawoodbridge.com/schedule-service-appointment2.htm?utm_source=google&utm_medium=organic&utm_campaign=gbp | L56: Monday 7:00 am - 6:00 pm~Tuesday 7:00 am - 6:00 pm~Wednesday 7:00 am - 6:00 pm~Thursday 7:00 am - 6:00 pm~Friday 7:00 am - 6:00 pm~Saturday 7:00 am - 5:00 pm~ | R56: 24-Hour Vehicle Drop Off | S56: Advanced Diagnostics | T56: Advanced Tune-Up Equip. | U56: Late Pickup | V56: Pet Friendly | W56: Shuttle Service | X56: 7034941800 | AE56: https://www.toyotatirecenter.com/?uid=BD2E2E5D-C7CE-6CD4-1BB7065E75945FD6 | AF56: 2022-07-07 | AG56: 2026-05-06 | AH56: Tracking Appends Entered | AI56: Existing params: utm_source, utm_medium, utm_campaign
A57: 45100 | B57: Priority Toyota Chesapeake | C57: 805 | D57: 757-614-1543 | E57: 1800 Greenbrier Parkway | F57: Chesapeake | G57: VA | H57: 23320 | I57: https://www.prioritytoyotachesapeake.com | J57: 24-Hour Vehicle Drop Off;Advanced Diagnostics;Advanced Tune-Up Equip.;Barista/Coffee Bar;Child Car Seat Check;Children's Play Area;Auto Detailing;Express Lube;Express Maintenance;On-Site Rental Vehicles;Parts Center;State Cert. Inspection | K57: https://www.prioritytoyotachesapeake.com/toyota-service-chesapeake-va.html | L57: Monday 7:00 am - 6:00 pm~Tuesday 7:00 am - 6:00 pm~Wednesday 7:00 am - 6:00 pm~Thursday 7:00 am - 6:00 pm~Friday 7:00 am - 6:00 pm~Saturday 8:00 am - 5:00 pm~ | M57: adam.brown@priorityauto.com | N57: Adam Brown | O57: Home of Priorities for Life | P57: Priority Toyota Chesapeake, where you can have it all! | R57: 24-Hour Vehicle Drop Off | S57: Advanced Diagnostics | T57: Advanced Tune-Up Equip. | U57: Barista/Coffee Bar | V57: Child Car Seat Check | W57: Children's Play Area | X57: 7573665000 | Y57: https://www.facebook.com/PriorityToyotaChesapeake | Z57: https://twitter.com/Priority_Toyota | AA57: https://www.youtube.com/c/PriorityToyotaofChesapeake/videos | AB57: https://www.yelp.com/biz/priority-toyota-chesapeake-chesapeake-3 | AC57: https://www.instagram.com/prioritytoyotachesapeake/ | AD57: https://www.prioritytoyotachesapeake.com/cars-for-sale-chesapeake-va.html | AE57: https://www.toyotatirecenter.com/?uid=47B922FB-DDC4-D4EA-608274AE5CD23A77 | AF57: 2023-06-13 | AG57: 2025-10-31 | AH57: No Issue Detected
A58: 01077 | B58: Springhill Toyota | C58: 50E | D58: 251-450-1000 | E58: 3062 Government Blvd. | F58: Mobile | G58: AL | H58: 36606 | I58: https://www.springhilltoyota.com | J58: Toyota Collision Center;Toyota Tire Center | K58: https://www.springhilltoyota.com/?schedule=true | L58: Monday 7:30 am - 5:30 pm~Tuesday 7:30 am - 5:30 pm~Wednesday 7:30 am - 5:30 pm~Thursday 7:30 am - 5:30 pm~Friday 7:30 am - 5:30 pm~Saturday 7:30 am - 2:00 pm~ | X58: 2514501000 | Y58: https://www.facebook.com/SpringhillToyota | Z58: https://twitter.com/SpghillToyota | AA58: https://www.youtube.com/springhilltoyota | AB58: https://www.yelp.com/biz/springhill-toyota-mobile | AE58: https://www.settirecenters.com/?uid=20F2D58F-C707-41AA-BEC2A9FFB7645C8A | AF58: 2022-04-11 | AG58: 2026-03-16 | AH58: Same as Dealer_URL (homepage) | AJ58: https://www.springhilltoyota.com/vehicle-finder-service/ | AK58: High
A59: 01079 | B59: High Country Toyota | C59: 50F | D59: 256-259-1159 | E59: 23030 John T. Reid Parkway | F59: Scottsboro | G59: AL | H59: 35769 | I59: https://www.highcountrytoyota.com | J59: 24-Hour Vehicle Drop Off;Advanced Diagnostics;Advanced Tune-Up Equip.;Barista/Coffee Bar;Child Car Seat Check;Complimentary Beverages;Auto Detailing;Express Lube;On-Site Rental Vehicles;Parts Center;Toyota Tire Center | K59: https://www.highcountrytoyota.com/service/schedule-service | L59: Monday 7:00 am - 6:00 pm~Tuesday 7:00 am - 6:00 pm~Wednesday 7:00 am - 6:00 pm~Thursday 7:00 am - 6:00 pm~Friday 7:00 am - 6:00 pm~Saturday 7:00 am - 4:00 pm~ | M59: serviceleads@drivehctoyota.com | R59: 24-Hour Vehicle Drop Off | S59: Advanced Diagnostics | T59: Advanced Tune-Up Equip. | U59: Barista/Coffee Bar | V59: Child Car Seat Check | W59: Complimentary Beverages | X59: 2562591159 | Y59: https://www.facebook.com/highcountryscottsboro | Z59: https://x.com/highcountryauto?lang=en | AA59: https://www.youtube.com/@HighCountryToyotaScottsboro | AB59: https://www.yelp.com/biz/high-country-toyota-scottsboro | AC59: https://www.instagram.com/highcountrytoyota/?hl=en | AE59: https://www.settirecenters.com/?uid=26214C3B-180D-46CA-B8C31D347DBEB789 | AF59: 2022-04-11 | AG59: 2026-07-07 | AH59: Error Page Entered | AI59: Status 403 at https://www.highcountrytoyota.com/service/schedule-service | AK59: None (no sitemap found; homepage links yielded no candidates)
A60: 01084 | B60: Eastern Shore Toyota | C60: 50E | D60: 251-250-0161 | E60: 29732 Frederick Blvd. | F60: Daphne | G60: AL | H60: 36526 | I60: https://www.easternshoretoyota.com | J60: 24-Hour Vehicle Drop Off;Barista/Coffee Bar;Children's Play Area;Complimentary Beverages;EV Charging Station;Pet Friendly;Car Wash;Toyota Tire Center | K60: https://www.easternshoretoyota.com/service/schedule-service/ | L60: Monday 7:00 am - 6:00 pm~Tuesday 7:00 am - 6:00 pm~Wednesday 7:00 am - 6:00 pm~Thursday 7:00 am - 6:00 pm~Friday 7:00 am - 6:00 pm~Saturday 7:00 am - 4:00 pm~ | M60: jfaison@easternshoretoyota.com | R60: 24-Hour Vehicle Drop Off | S60: Barista/Coffee Bar | T60: Children's Play Area | U60: Complimentary Beverages | V60: EV Charging Station | W60: Pet Friendly | X60: 2516251919 | Y60: https://www.facebook.com/EasternShoreToyota | Z60: https://twitter.com/toyotaes | AA60: https://www.youtube.com/channel/UC7pqw4YfWnnlrcD9k2Lq6qw/videos | AB60: https://www.yelp.com/biz/eastern-shore-toyota-daphne | AC60: https://instagram.com/EasternShoreToyota | AE60: https://www.settirecenters.com/?uid=EB5509E7-0E76-46A6-AF20F24EE1771691 | AF60: 2022-04-11 | AG60: 2026-06-08 | AH60: No Issue Detected
A61: 01089 | B61: Toyota of Sylacauga | C61: 50F | D61: 256-245-5251 | E61: 39765 Highway 280 | F61: Sylacauga | G61: AL | H61: 35150 | I61: https://www.toyotaofsylacauga.com | J61: 24-Hour Vehicle Drop Off;Advanced Diagnostics;Advanced Tune-Up Equip.;Barista/Coffee Bar;Complimentary Beverages;Pet Friendly;On-Site Rental Vehicles | K61: https://www.toyotaofsylacauga.com/service/schedule-service/ | L61: Monday 7:30 am - 5:30 pm~Tuesday 7:30 am - 5:30 pm~Wednesday 7:30 am - 5:30 pm~Thursday 7:30 am - 5:30 pm~Friday 7:30 am - 5:30 pm~Saturday 7:30 am - 3:00 pm~ | R61: 24-Hour Vehicle Drop Off | S61: Advanced Diagnostics | T61: Advanced Tune-Up Equip. | U61: Barista/Coffee Bar | V61: Complimentary Beverages | W61: Pet Friendly | X61: 2562455251 | AE61: https://www.settirecenters.com/?uid=226A36A3-FA8A-41C1-96EDE83A89A271E1 | AF61: 2022-04-11 | AG61: 2026-07-07 | AH61: No Issue Detected
A62: 01090 | B62: Hoover Toyota | C62: 50F | D62: 205-978-2600 | E62: 2686 Highway 150 | F62: Hoover | G62: AL | H62: 35244 | I62: https://www.hoovertoyota.com | K62: https://www.hoovertoyota.com/schedule-service/ | L62: Monday 6:00 am - 6:00 pm~Tuesday 6:00 am - 6:00 pm~Wednesday 6:00 am - 6:00 pm~Thursday 6:00 am - 6:00 pm~Friday 6:00 am - 6:00 pm~Saturday 6:00 am - 3:00 pm~ | X62: 2059782600 | AE62: https://www.settirecenters.com/?uid=0030751A-BE38-4C00-B90F205231CE74AE | AF62: 2022-04-11 | AG62: 2026-06-08 | AH62: No Issue Detected
A63: 01095 | B63: Toyota of Montgomery | C63: 50E | D63: 334-272-7147 | E63: 911 Eastern Blvd. | F63: Montgomery | G63: AL | H63: 36117 | I63: https://www.toyotamontgomery.com | J63: Express Maintenance | K63: https://www.toyotamontgomery.com/schedule-service.html | L63: Monday 7:00 am - 6:00 pm~Tuesday 7:00 am - 6:00 pm~Wednesday 7:00 am - 6:00 pm~Thursday 7:00 am - 6:00 pm~Friday 7:00 am - 6:00 pm~Saturday 7:00 am - 3:00 pm~ | X63: 3342727147 | AE63: https://www.settirecenters.com/?uid=FDB7097E-C0DB-42C7-917AD1FC344EE1D1 | AF63: 2025-11-25 | AG63: 2025-12-01 | AH63: No Issue Detected
A64: 02016 | B64: Big Two Toyota of Chandler | C64: 151 | D64: 480-898-6010 | E64: 1250 S. Gilbert Road | F64: Chandler | G64: AZ | H64: 85286 | I64: https://www.bigtwotoyota.com | J64: 24-Hour Vehicle Drop Off;Advanced Diagnostics;Advanced Tune-Up Equip.;Barista/Coffee Bar;Children's Play Area;Complimentary Beverages;Auto Detailing;Car Wash;Express Lube;Parts Center;Toyota Tire Center | K64: https://www.bigtwotoyota.com/service/appointments.htm | L64: Monday 7:00 am - 6:00 pm~Tuesday 7:00 am - 6:00 pm~Wednesday 7:00 am - 6:00 pm~Thursday 7:00 am - 6:00 pm~Friday 7:00 am - 6:00 pm~Saturday 7:00 am - 6:00 pm~ | M64: brett.maxwell@bigtwo.com | O64: Service Director | R64: 24-Hour Vehicle Drop Off | S64: Advanced Diagnostics | T64: Advanced Tune-Up Equip. | U64: Barista/Coffee Bar | V64: Children's Play Area | W64: Complimentary Beverages | X64: 4808986000 | Y64: https://www.facebook.com/bigtwotoyota | Z64: https://twitter.com/BigTwoToyota | AA64: https://www.youtube.com/user/bigtwotoyota | AB64: https://www.yelp.com/biz/big-two-toyota-scion-of-chandler-chandler-2 | AE64: https://www.toyotatirecenter.com/?uid=E5EEFC7E-03DB-8D5A-B8CF4BA352DFA864 | AF64: 2022-04-11 | AG64: 2026-05-04 | AH64: No Issue Detected
A65: 02036 | B65: Camelback Toyota | C65: 151 | D65: 602-266-2611 | E65: 1550 East Camelback Road | F65: Phoenix | G65: AZ | H65: 85014 | I65: https://www.camelbacktoyota.com | J65: Advanced Diagnostics;Advanced Tune-Up Equip.;Barista/Coffee Bar;Children's Play Area;Complimentary Beverages;Complimentary Ride Share;Auto Detailing;On-Site Rental Vehicles;Parts Center;RAV4 EV Service;Toyota Collision Center;Toyota Tire Center;Board of Governors Award;Pres. Cabinet Award;Pres. Customer 1st Award | K65: https://camelbacktoyota.svcapt.com/ | L65: Monday 7:00 am - 6:00 pm~Tuesday 7:00 am - 6:00 pm~Wednesday 7:00 am - 6:00 pm~Thursday 7:00 am - 6:00 pm~Friday 7:00 am - 6:00 pm~Saturday 7:00 am - 4:00 pm~ | M65: CBTSERVICE@VTAIG.COM | O65: Izad Far | P65: Service Director | R65: Advanced Diagnostics | S65: Advanced Tune-Up Equip. | T65: Barista/Coffee Bar | U65: Children's Play Area | V65: Complimentary Beverages | W65: Complimentary Ride Share | X65: 6022642841 | Y65: https://www.facebook.com/CamelbackToyota | Z65: https://twitter.com/CamelbackToyota | AA65: https://www.youtube.com/user/CamelbackToyota | AB65: https://www.yelp.com/biz/camelback-toyota-phoenix-3 | AC65: https://instagram.com/camelbacktoyota | AE65: https://www.toyotatirecenter.com/?uid=92068CA7-B031-FDAD-2C0A65C39C3CABDE | AF65: 2022-04-11 | AG65: 2026-06-08 | AH65: Different Domain (Unverified) | AI65: Hosted on svcapt.com, not on dealer's own domain (camelbacktoyota.com), but not on the known 3rd-party scheduler list -- verify manually
A66: 02038 | B66: Hatch Toyota | C66: 156 | D66: 928-537-5755 | E66: 1051 North Automall Parkway | F66: Show Low | G66: AZ | H66: 85901 | I66: https://www.hatchtoyota.com | J66: 24-Hour Vehicle Drop Off;Advanced Diagnostics;Advanced Tune-Up Equip.;Barista/Coffee Bar;Collision Loaner Vehicle;Complimentary Beverages;Express Lube;Express Maintenance;On-Site Rental Vehicles;Parts Center;Toyota Tire Center;Pres. Customer 1st Award | K66: https://www.hatchtoyota.com/service-appointment/ | L66: Monday 8:00 am - 5:00 pm~Tuesday 8:00 am - 5:00 pm~Wednesday 8:00 am - 5:00 pm~Thursday 8:00 am - 5:00 pm~Friday 8:00 am - 5:00 pm~Saturday 8:00 am - 5:00 pm~ | M66: cstearns@hatchtoyota.com | O66: Bob Genet | P66: Service Manager | R66: 24-Hour Vehicle Drop Off | S66: Advanced Diagnostics | T66: Advanced Tune-Up Equip. | U66: Barista/Coffee Bar | V66: Collision Loaner Vehicle | W66: Complimentary Beverages | X66: 9285375755 | Y66: https://www.facebook.com/HatchToyota | Z66: https://twitter.com/hatchtoyota | AA66: https://www.youtube.com/hatchtoyota | AB66: https://www.yelp.com/biz/hatch-toyota-show-low | AC66: https://instagram.com/hatchtoyota | AF66: 2022-04-11 | AG66: 2026-06-08 | AH66: Error Page Entered | AI66: Status 403 at https://www.hatchtoyota.com/service-appointment/ | AK66: None (no sitemap found; homepage links yielded no candidates)
A67: 02053 | B67: Berge Toyota | C67: 151 | D67: 480-655-4400 | E67: 2020 W Riverview Auto Dr | F67: Mesa | G67: AZ | H67: 85201 | I67: https://www.bergetoyota.com | J67: 24-Hour Vehicle Drop Off;Advanced Diagnostics;Barista/Coffee Bar;Children's Play Area;Complimentary Ride Share;Complimentary Snacks;Parts Center;Toyota Tire Center | K67: https://www.bergetoyota.com | L67: Monday 7:00 am - 6:00 pm~Tuesday 7:00 am - 6:00 pm~Wednesday 7:00 am - 6:00 pm~Thursday 7:00 am - 6:00 pm~Friday 7:00 am - 6:00 pm~Saturday 7:00 am - 4:00 pm~ | M67: rtyservice@riverviewtoyota.com | O67: John Stanley | P67: General Manager | R67: 24-Hour Vehicle Drop Off | S67: Advanced Diagnostics | T67: Barista/Coffee Bar | U67: Children's Play Area | V67: Complimentary Ride Share | W67: Complimentary Snacks | X67: 4806554400 | Y67: https://www.facebook.com/BrentBergesRiverviewToyota | Z67: https://twitter.com/RiverviewToyota | AA67: https://www.youtube.com/user/BrentBergeToyota/about | AB67: https://www.yelp.com/biz/riverview-toyota-mesa | AE67: https://www.toyotatirecenter.com/?uid=DB51927B-A9A8-B7F8-E8F01057DF7D21F3 | AF67: 2022-04-11 | AG67: 2026-06-08 | AH67: Same as Dealer_URL (homepage) | AJ67: https://www.bergetoyota.com/service/toyota-maintenance-schedule/ | AK67: High
A68: 03068 | B68: Caldwell Toyota | C68: 60I | D68: 501-382-7684 | E68: 1355 Exchange Avenue | F68: Conway | G68: AR | H68: 72032 | I68: https://www.caldwelltoyota.com | J68: Advanced Diagnostics;Advanced Tune-Up Equip.;Barista/Coffee Bar;Children's Play Area;Complimentary Beverages;EV Charging Station;Express Maintenance;Parts Center;Toyota Tire Center;LEED Certified Facility;Pres. Customer 1st Award | K68: https://www.caldwell-toyota.com/schedule-service.htm | L68: Monday 7:00 am - 6:00 pm~Tuesday 7:00 am - 6:00 pm~Wednesday 7:00 am - 6:00 pm~Thursday 7:00 am - 6:00 pm~Friday 7:00 am - 6:00 pm~Saturday 7:00 am - 6:00 pm~ | R68: Advanced Diagnostics | S68: Advanced Tune-Up Equip. | T68: Barista/Coffee Bar | U68: Children's Play Area | V68: Complimentary Beverages | W68: EV Charging Station | X68: 5013273900 | Y68: https://www.facebook.com/CaldwellToyotaScion | Z68: https://twitter.com/caldwelltoyota | AA68: https://www.youtube.com/user/caldwelltoyotaconway | AB68: https://www.yelp.com/biz/caldwell-toyota-conway-2 | AC68: https://www.instagram.com/caldwelltoyota | AE68: https://www.toyotatirecenter.com/?uid=1763FF8A-782B-CB09-0EF5134A693DABEE | AF68: 2022-04-11 | AG68: 2026-06-23 | AH68: Different Domain (Unverified) | AI68: Hosted on caldwell-toyota.com, not on dealer's own domain (caldwelltoyota.com), but not on the known 3rd-party scheduler list -- verify manually
A69: 04046 | B69: Toyota Salinas | C69: 121 | D69: 831-444-0700 | E69: 700 Auto Center Circle | F69: Salinas | G69: CA | H69: 93907 | I69: https://www.toyotasalinas.com | J69: Advanced Diagnostics;Advanced Tune-Up Equip.;Complimentary Ride Share;EV Charging Station;Late Pickup;Pet Friendly;Express Lube;On-Site Rental Vehicles | K69: https://www.toyotasalinas.com/toyota-schedule-service/ | L69: Monday 7:00 am - 6:00 pm~Tuesday 7:00 am - 6:00 pm~Wednesday 7:00 am - 6:00 pm~Thursday 7:00 am - 6:00 pm~Friday 7:00 am - 6:00 pm~Saturday 7:00 am - 6:00 pm~Sunday 7:00 am - 6:00 pm | M69: SERVICE@TOYOTASALINAS.COM | R69: Advanced Diagnostics | S69: Advanced Tune-Up Equip. | T69: Complimentary Ride Share | U69: EV Charging Station | V69: Late Pickup | W69: Pet Friendly | X69: 8314440700 | AF69: 2022-07-07 | AG69: 2026-06-08 | AH69: Error Page Entered | AI69: Status 403 at https://www.toyotasalinas.com/toyota-schedule-service/ | AK69: None (no sitemap found; homepage links yielded no candidates)
A70: 04051 | B70: Toyota Walnut Creek | C70: 122 | D70: 925-357-3700 | E70: 2100 North Broadway | F70: Walnut Creek | G70: CA | H70: 94596 | I70: https://www.toyotawc.com | J70: Advanced Diagnostics;Advanced Tune-Up Equip.;Barista/Coffee Bar;Complimentary Ride Share;Contactless Service;EV Charging Station;Express Lube;Express Maintenance;On-Site Rental Vehicles;Parts Center;RAV4 EV Service;Toyota Tire Center | K70: https://www.toyotawc.com/#modal-scheduleservice | L70: Monday 6:00 am - 8:00 pm~Tuesday 6:00 am - 8:00 pm~Wednesday 6:00 am - 8:00 pm~Thursday 6:00 am - 8:00 pm~Friday 6:00 am - 8:00 pm~~ | O70: Larry Crewse | P70: Service Director | R70: Advanced Diagnostics | S70: Advanced Tune-Up Equip. | T70: Barista/Coffee Bar | U70: Complimentary Ride Share | V70: Contactless Service | W70: EV Charging Station | X70: 9259337440 | AE70: https://www.toyotatirecenter.com/?uid=31C292DB-782B-CB08-A50D345D9E63E692 | AF70: 2022-04-11 | AG70: 2026-06-08 | AH70: Same as Dealer_URL (homepage) | AJ70: https://www.toyotawc.com#schedule-service | AK70: High
A71: 04076 | B71: Toyota of The Desert | C71: 117 | D71: 760-328-0871 | E71: 68105 Kyle Road | F71: Cathedral City | G71: CA | H71: 92234 | I71: https://www.toyotaofthedesert.com | J71: 24-Hour Vehicle Drop Off;Advanced Diagnostics;Advanced Tune-Up Equip.;Barista/Coffee Bar;Children's Play Area;Complimentary Beverages;Auto Detailing;Car Wash;Express Lube;Express Maintenance;On-Site Rental Vehicles;Parts Center;Pres. Customer 1st Award | K71: https://www.toyotaofthedesert.com/service/schedule-service/ | L71: Monday 7:00 am - 6:00 pm~Tuesday 7:00 am - 6:00 pm~Wednesday 7:00 am - 6:00 pm~Thursday 7:00 am - 6:00 pm~Friday 7:00 am - 6:00 pm~Saturday 7:00 am - 6:00 pm~ | O71: Robert Dumas | P71: Service Director | R71: 24-Hour Vehicle Drop Off | S71: Advanced Diagnostics | T71: Advanced Tune-Up Equip. | U71: Barista/Coffee Bar | V71: Children's Play Area | W71: Complimentary Beverages | X71: 7603280871 | Y71: https://www.facebook.com/Toyota-of-the-Desert-165919426756363 | Z71: https://twitter.com/Toyota_Desert | AA71: https://www.youtube.com/channel/UCucDAn4oWNpnE04EBhq8FAQ | AB71: https://www.yelp.com/biz/toyota-of-the-desert-cathedral-city | AF71: 2022-04-11 | AG71: 2026-06-08 | AH71: No Issue Detected
A72: 04118 | B72: Toyota of Santa Barbara | C72: 118 | D72: 805-215-1123 | E72: 5611 Hollister Avenue | F72: Goleta | G72: CA | H72: 93117 | I72: https://www.toyotaofsantabarbara.com | J72: Advanced Diagnostics;Advanced Tune-Up Equip.;Barista/Coffee Bar;Complimentary Beverages;Late Pickup;Pet Friendly;On-Site Rental Vehicles | K72: https://www.toyotaofsantabarbara.com/service-appointment/ | L72: Monday 7:00 am - 6:00 pm~Tuesday 7:00 am - 6:00 pm~Wednesday 7:00 am - 6:00 pm~Thursday 7:00 am - 6:00 pm~Friday 7:00 am - 6:00 pm~Saturday 8:00 am - 4:00 pm~ | O72: Your Toyota Service Team | R72: Advanced Diagnostics | S72: Advanced Tune-Up Equip. | T72: Barista/Coffee Bar | U72: Complimentary Beverages | V72: Late Pickup | W72: Pet Friendly | X72: 8059675611 | AE72: https://www.toyotatirecenter.com/?uid=974DE813-B716-73C7-3A7D5510C63F4624 | AF72: 2022-04-11 | AG72: 2026-05-06 | AH72: Error Page Entered | AI72: Status 403 at https://www.toyotaofsantabarbara.com/service-appointment/ | AK72: None (no sitemap found; homepage links yielded no candidates)
A73: 04120 | B73: Lodi Toyota | C73: 125 | D73: 209-367-6500 | E73: 1020 S. Beckman Road | F73: Lodi | G73: CA | H73: 95240 | I73: https://www.loditoyota.com | J73: Online Scheduling | K73: https://www.loditoyota.com | L73: Monday 7:00 am - 6:00 pm~Tuesday 7:00 am - 6:00 pm~Wednesday 7:00 am - 6:00 pm~Thursday 7:00 am - 6:00 pm~Friday 7:00 am - 6:00 pm~Saturday 7:00 am - 4:00 pm~ | R73: Online Scheduling | X73: 2096424022 | AE73: https://www.toyotatirecenter.com/?uid=3C237A9C-A098-4448-B59B1C28BA803287 | AF73: 2022-10-04 | AG73: 2026-06-08 | AH73: Same as Dealer_URL (homepage) | AJ73: https://www.loditoyota.com/service-one-service-scheduler.htm | AK73: High
A74: 04456 | B74: Toyota of El Cajon | C74: 114 | D74: 619-590-1061 | E74: 965 Arnele Avenue | F74: El Cajon | G74: CA | H74: 92020 | I74: https://www.toyotaofelcajon.com | J74: 24-Hour Vehicle Drop Off;Advanced Diagnostics;Barista/Coffee Bar;Children's Play Area;Contactless Service;Online Scheduling;Auto Detailing;Express Lube;On-Site Rental Vehicles;Parts Center;RAV4 EV Service;State Cert. Inspection;LEED Certified Facility;Pres. Customer 1st Award | K74: https://conscheduling.tekioncloud.com/consumer-scheduling/sign-in/phone?accessToken=kaminskymotors_891_7379 | L74: Monday 7:00 am - 6:00 pm~Tuesday 7:00 am - 6:00 pm~Wednesday 7:00 am - 6:00 pm~Thursday 7:00 am - 6:00 pm~Friday 7:00 am - 6:00 pm~Saturday 7:00 am - 5:00 pm~ | O74: Jeff Anderson | P74: Service Director | R74: 24-Hour Vehicle Drop Off | S74: Advanced Diagnostics | T74: Barista/Coffee Bar | U74: Children's Play Area | V74: Contactless Service | W74: Online Scheduling | X74: 6192703000 | Y74: https://www.facebook.com/ToyotaOfElCajon/ | Z74: https://twitter.com/ToyotaElCajon | AA74: https://www.youtube.com/channel/UCURFZ_qqR2AXbLutzsShUmQ | AB74: https://www.yelp.com/biz/toyota-of-el-cajon-el-cajon | AC74: https://www.instagram.com/toyotaelcajon/?hl=en | AE74: https://www.toyotatirecenter.com/?uid=A18FFB65-6635-4009-AA942173472B9AFE | AF74: 2022-04-11 | AG74: 2026-07-07 | AH74: 3rd Party Scheduler | AI74: Hosted on tekioncloud.com, not on dealer's own domain
A75: 04508 | B75: Manhattan Beach Toyota | C75: 112 | D75: 310-683-0041 | E75: 1500 N. Sepulveda Blvd | F75: Manhattan Beach | G75: CA | H75: 90266 | I75: https://www.manhattanbeachtoyota.com | J75: Advanced Diagnostics;Advanced Tune-Up Equip.;Spanish Speaking;Vending Machines;On-Site Rental Vehicles;Parts Center;RAV4 EV Service;Toyota Tire Center;Pres. Customer 1st Award | K75: https://www.manhattanbeachtoyota.com/#schedule-service | L75: Monday 7:00 am - 7:00 pm~Tuesday 7:00 am - 7:00 pm~Wednesday 7:00 am - 7:00 pm~Thursday 7:00 am - 7:00 pm~Friday 7:00 am - 7:00 pm~Saturday 7:00 am - 6:00 pm~ | M75: jwillet@manhattanbeachtoyota.com | O75: Jeffrey Willet | P75: Service Director | R75: Advanced Diagnostics | S75: Advanced Tune-Up Equip. | T75: Spanish Speaking | U75: Vending Machines | X75: 3105464848 | Y75: https://www.facebook.com/ManhattanBeachToyota | Z75: https://twitter.com/mhbeachtoy | AA75: https://www.youtube.com/user/mbeachtoyota/ | AB75: https://www.yelp.com/biz/manhattan-beach-toyota-manhattan-beach-2 | AC75: https://www.instagram.com/manhattan_beach_toyota/ | AD75: https://manhattanbeachtoyota.roadster.com/ | AE75: https://www.toyotatirecenter.com/?uid=10AE84AB-DDF3-16ED-6398E90958026BC7 | AF75: 2022-04-11 | AG75: 2026-05-06 | AH75: Same as Dealer_URL (homepage) | AJ75: https://www.manhattanbeachtoyota.com/schedule-service | AK75: High
A76: 04638 | B76: AutoNation Toyota Irvine | C76: 116 | D76: 949-768-0688 | E76: 9101 Research Drive | F76: Irvine | G76: CA | H76: 92618 | I76: https://www.autonationtoyotairvine.com | J76: 24-Hour Vehicle Drop Off;Advanced Diagnostics;Advanced Tune-Up Equip.;Children's Play Area;Complimentary Beverages;Complimentary Snacks;Express Maintenance;Parts Center;RAV4 EV Service;Toyota Tire Center | K76: https://www.autonationtoyotairvine.com/service/schedule/appointment.htm | L76: Monday 7:00 am - 6:00 pm~Tuesday 7:00 am - 6:00 pm~Wednesday 7:00 am - 6:00 pm~Thursday 7:00 am - 6:00 pm~Friday 7:00 am - 6:00 pm~Saturday 7:00 am - 5:00 pm~ | M76: lewisd4@autonation.com | O76: Denise Lewis | P76: Service Manager | R76: 24-Hour Vehicle Drop Off | S76: Advanced Diagnostics | T76: Advanced Tune-Up Equip. | U76: Children's Play Area | V76: Complimentary Beverages | W76: Complimentary Snacks | X76: 9492878766 | Y76: https://www.facebook.com/AutoNationToyotaScionIrvine | Z76: https://twitter.com/ANToyotaIrvine | AA76: https://www.youtube.com/channel/UCCvShBpB2DOdBiaeNRBuWQw | AB76: https://www.yelp.com/biz/autonation-toyota-irvine-irvine-2 | AE76: https://www.toyotatirecenter.com/?uid=B969DD03-5D0F-4A0D-98026AC72F5B5C7E | AF76: 2022-04-11 | AG76: 2026-06-10 | AH76: No Issue Detected
A77: 04640 | B77: AutoNation Toyota Buena Park | C77: 111 | D77: 714-522-6144 | E77: 6400 Beach Blvd. | F77: Buena Park | G77: CA | H77: 90621 | I77: https://www.autonationtoyotabuenapark.com | J77: 24-Hour Vehicle Drop Off;Advanced Diagnostics;Advanced Tune-Up Equip.;Online Scheduling;Shuttle Service;Spanish Speaking;Express Maintenance;Parts Center;RAV4 EV Service;Toyota Tire Center | K77: https://www.autonationtoyotabuenapark.com/service/schedule/appointment.htm | L77: Monday 7:00 am - 7:00 pm~Tuesday 7:00 am - 7:00 pm~Wednesday 7:00 am - 7:00 pm~Thursday 7:00 am - 7:00 pm~Friday 7:00 am - 7:00 pm~Saturday 7:00 am - 5:00 pm~ | M77: keoroghlians@autonation.com | O77: Your Service Specialists | R77: 24-Hour Vehicle Drop Off | S77: Advanced Diagnostics | T77: Advanced Tune-Up Equip. | U77: Online Scheduling | V77: Shuttle Service | W77: Spanish Speaking | X77: 7146275562 | Y77: https://www.facebook.com/AutoNationToyotaScionBuenaPark | Z77: https://twitter.com/ANToyotaBuenaPk | AB77: https://www.yelp.com/biz/autonation-toyota-buena-park-buena-park | AE77: https://www.toyotatirecenter.com/?uid=9F11AA15-E45A-6E27-AD9299C36EBC149F | AF77: 2022-04-11 | AG77: 2026-05-06 | AH77: No Issue Detected
A78: 04726 | B78: West Coast Toyota of Long Beach | C78: 111 | D78: 562-733-5200 | E78: 3399 E. Willow Street | F78: Long Beach | G78: CA | H78: 90806 | I78: https://www.westcoasttoyotalb.com | J78: Advanced Diagnostics;Advanced Tune-Up Equip.;Child Car Seat Check;Complimentary Ride Share;Online Scheduling;Pick Up/Delivery Options;Express Lube;Express Maintenance;On-Site Rental Vehicles;Parts Center;Toyota Tire Center | K78: https://www.westcoasttoyotalb.com/service/schedule-service/ | L78: Monday 7:00 am - 6:00 pm~Tuesday 7:00 am - 6:00 pm~Wednesday 7:00 am - 6:00 pm~Thursday 7:00 am - 6:00 pm~Friday 7:00 am - 6:00 pm~Saturday 7:00 am - 5:00 pm~ | O78: Fred Potter | P78: Service Manager | R78: Advanced Diagnostics | S78: Advanced Tune-Up Equip. | T78: Child Car Seat Check | U78: Complimentary Ride Share | V78: Online Scheduling | W78: Pick Up/Delivery Options | X78: 5624944444 | AE78: https://www.toyotatirecenter.com/?uid=F63F8CFC-657E-48D2-A9500D8593076905 | AF78: 2022-04-11 | AG78: 2026-06-08 | AH78: No Issue Detected
A79: 04739 | B79: Toyota of Downtown LA | C79: 112 | D79: 833-315-3922 | E79: 1901 S. Figueroa Street | F79: Los Angeles | G79: CA | H79: 90007 | I79: https://www.toyotaofdowntownla.com | J79: 24-Hour Vehicle Drop Off;Advanced Diagnostics;Advanced Tune-Up Equip.;Barista/Coffee Bar;Children's Play Area;Complimentary Ride Share;Express Lube;Express Maintenance;On-Site Rental Vehicles;Parts Center;Toyota Tire Center | K79: https://www.toyotaofdowntownla.com/#modal-scheduleservice | L79: Monday 6:00 am - 6:00 pm~Tuesday 6:00 am - 6:00 pm~Wednesday 6:00 am - 6:00 pm~Thursday 6:00 am - 6:00 pm~Friday 6:00 am - 6:00 pm~Saturday 6:00 am - 5:00 pm~ | O79: Your DTLA Service Team | R79: 24-Hour Vehicle Drop Off | S79: Advanced Diagnostics | T79: Advanced Tune-Up Equip. | U79: Barista/Coffee Bar | V79: Children's Play Area | W79: Complimentary Ride Share | X79: 2139862011 | AA79: https://www.youtube.com/@ToyotaCentral/videos | AB79: https://www.yelp.com/biz/toyota-of-downtown-los-angeles | AE79: https://www.toyotatirecenter.com/?uid=F120F24A-EAE0-B398-E98CAD03B9DAB1A3 | AF79: 2022-04-11 | AG79: 2026-06-08 | AH79: Same as Dealer_URL (homepage) | AJ79: https://www.toyotaofdowntownla.com/ScheduleService | AK79: High
A80: 05043 | B80: Stapp Interstate Toyota, Inc. | C80: 152 | D80: 720-864-2500 | E80: 8019 Raspberry Way | F80: Frederick | G80: CO | H80: 80504 | I80: https://www.interstatetoyota.com | J80: 24-Hour Vehicle Drop Off;Advanced Diagnostics;Advanced Tune-Up Equip.;Contactless Service;Online Scheduling;Pet Friendly;Express Lube;Parts Center;RAV4 EV Service;Toyota Tire Center;Pres. Customer 1st Award | K80: https://www.interstatetoyota.com/serviceappt.html | L80: Monday 7:00 am - 6:00 pm~Tuesday 7:00 am - 6:00 pm~Wednesday 7:00 am - 6:00 pm~Thursday 7:00 am - 6:00 pm~Friday 7:00 am - 6:00 pm~Saturday 8:00 am - 5:00 pm~ | M80: Service@interstatetoyota.com | O80: Ryan Zamudio | P80: Service Manager | R80: 24-Hour Vehicle Drop Off | S80: Advanced Diagnostics | T80: Advanced Tune-Up Equip. | U80: Contactless Service | V80: Online Scheduling | W80: Pet Friendly | X80: 3037761743 | Y80: https://www.facebook.com/InterstateToyota | Z80: https://twitter.com/stappIToyota | AA80: https://www.youtube.com/channel/UCN4svdAaBFnY0T9EmwXiJug | AB80: https://www.yelp.com/biz/stapp-interstate-toyota-scion-frederick | AC80: https://www.instagram.com/stappitoyota/ | AE80: https://www.toyotatirecenter.com/?uid=015A5E94-C3BA-8686-86BC7275A5D9486B | AF80: 2022-04-11 | AG80: 2023-05-16 | AH80: No Issue Detected
A81: 05051 | B81: Pueblo Toyota | C81: 152 | D81: 719-543-1719 | E81: 2220 US Highway 50 West | F81: Pueblo | G81: CO | H81: 81008 | I81: https://www.pueblotoyota.com | J81: 24-Hour Vehicle Drop Off;Advanced Diagnostics;Advanced Tune-Up Equip.;Barista/Coffee Bar;Children's Play Area;EV Charging Station;Express Lube;Express Maintenance;On-Site Rental Vehicles;Parts Center;Toyota Tire Center;LEED Certified Facility;Pres. Customer 1st Award | K81: https://www.pueblotoyota.com/Schedule-Service.html | L81: Monday 7:00 am - 6:00 pm~Tuesday 7:00 am - 6:00 pm~Wednesday 7:00 am - 6:00 pm~Thursday 7:00 am - 6:00 pm~Friday 7:00 am - 6:00 pm~Saturday 8:00 am - 5:00 pm~ | M81: dsena@pueblotoyota.com | O81: Devin Sena | P81: Service Manager | R81: 24-Hour Vehicle Drop Off | S81: Advanced Diagnostics | T81: Advanced Tune-Up Equip. | U81: Barista/Coffee Bar | V81: Children's Play Area | W81: EV Charging Station | X81: 7195431719 | Y81: https://www.facebook.com/PuebloToyotas | Z81: https://twitter.com/PuebloToyota | AA81: https://www.youtube.com/channel/UC7ynGXLP9xl41G4NtesWtnA | AB81: https://www.yelp.com/biz/pueblo-toyota-inc-pueblo | AE81: https://www.toyotatirecenter.com/?uid=01558009-9087-93F6-6EB0FA1E9976F27E | AF81: 2022-04-11 | AG81: 2026-05-14 | AH81: No Issue Detected
A82: 05074 | B82: Stevinson Toyota West | C82: 152 | D82: 720-902-9966 | E82: 780 Denver W Colorado Mills Bl | F82: Lakewood | G82: CO | H82: 80401 | I82: https://www.stevinsontoyotawest.com | J82: 24-Hour Vehicle Drop Off;Advanced Diagnostics;Advanced Tune-Up Equip.;Barista/Coffee Bar;Children's Play Area;Complimentary Beverages;Express Lube;Express Maintenance;On-Site Rental Vehicles | K82: https://www.stevinsontoyotawest.com/schedule-service | L82: Monday 7:00 am - 6:00 pm~Tuesday 7:00 am - 6:00 pm~Wednesday 7:00 am - 6:00 pm~Thursday 7:00 am - 6:00 pm~Friday 7:00 am - 6:00 pm~Saturday 8:00 am - 5:00 pm~ | O82: Service Manager | R82: 24-Hour Vehicle Drop Off | S82: Advanced Diagnostics | T82: Advanced Tune-Up Equip. | U82: Barista/Coffee Bar | V82: Children's Play Area | W82: Complimentary Beverages | X82: 3032770550 | AE82: https://www.toyotatirecenter.com/?uid=CE3F38F8-F20A-40E4-E86871F2DC415287 | AF82: 2022-04-11 | AG82: 2026-07-07 | AH82: Redirect Drops Query String | AI82: https://www.stevinsontoyotawest.com/schedule-service -> https://www.stevinsontoyotawest.com/schedule-service.htm (redirect drops query strings; confirmed by appending test params: https://www.stevinsontoyotawest.com/schedule-service?siteid=test&utm_source=test -> https://www.stevinsontoyotawest.com/schedule-service.htm)
A83: 05079 | B83: Vista Toyota Delta | C83: 157 | D83: 970-874-4444 | E83: 750 E. Highway 92 | F83: Delta | G83: CO | H83: 81416 | I83: https://www.vistatoyotaco.com | L83: Monday 7:15 am - 5:30 pm~Tuesday 7:15 am - 5:30 pm~Wednesday 7:15 am - 5:30 pm~Thursday 7:15 am - 5:30 pm~Friday 7:15 am - 5:30 pm~Saturday 8:00 am - 2:00 pm~ | X83: 9708744444 | AE83: https://www.toyotatirecenter.com/?uid=A95A4166-34C9-4DD0-8B672B786EB16DFE | AF83: 2025-10-13 | AG83: 2026-07-07 | AH83: No URL | AJ83: https://www.vistatoyotaco.com/service/schedule-service/ | AK83: High
A84: 06025 | B84: Lynch Toyota | C84: 164 | D84: 860-647-0402 | E84: 179 Tolland Turnpike | F84: Manchester | G84: CT | H84: 06040 | I84: https://www.lynchtoyota.com | J84: Spanish Speaking;Parts Center;Toyota Collision Center;Toyota Tire Center;Pres. Customer 1st Award | K84: https://www.lynchtoyota.com/service/schedule-service/ | L84: Monday 7:30 am - 6:00 pm~Tuesday 7:30 am - 6:00 pm~Wednesday 7:30 am - 6:00 pm~Thursday 7:30 am - 6:00 pm~Friday 7:30 am - 6:00 pm~Saturday 7:00 am - 3:00 pm~ | M84: service@lynchtoyota.com | O84: Your Service Professionals | R84: Spanish Speaking | X84: 8606464321 | Y84: https://www.facebook.com/LynchToyota | Z84: https://twitter.com/LynchToyotaCT | AA84: https://www.youtube.com/user/LynchToyotaCT | AB84: https://www.yelp.com/biz/lynch-toyota-manchester | AC84: https://instagram.com/lynchtoyota | AE84: https://www.toyotatirecenter.com/?uid=78B1AABC-DF1E-04C0-E0B0F04B062AF7DE | AF84: 2022-04-11 | AG84: 2025-10-31 | AH84: No Issue Detected
A85: 06043 | B85: Westbrook Toyota | C85: 164 | D85: 800-628-4471 | E85: 80 Flat Rock Place | F85: Westbrook | G85: CT | H85: 06498 | I85: https://www.westbrooktoyota.com | J85: 24-Hour Vehicle Drop Off;Advanced Diagnostics;Advanced Tune-Up Equip.;Barista/Coffee Bar;Children's Play Area;Complimentary Beverages;Auto Detailing;Car Wash;Parts Center;Toyota Tire Center;LEED Certified Facility;Pres. Customer 1st Award | K85: https://www.westbrooktoyota.com/#modal-scheduleservice | L85: Monday 7:30 am - 5:00 pm~Tuesday 7:30 am - 5:00 pm~Wednesday 7:30 am - 5:00 pm~Thursday 7:30 am - 5:00 pm~Friday 7:30 am - 5:00 pm~Saturday 7:30 am - 5:00 pm~ | M85: jhall@westbrooktoyota.com | O85: Your Service Professional | P85: Westbrook Toyota | R85: 24-Hour Vehicle Drop Off | S85: Advanced Diagnostics | T85: Advanced Tune-Up Equip. | U85: Barista/Coffee Bar | V85: Children's Play Area | W85: Complimentary Beverages | X85: 8603886991 | Y85: https://www.facebook.com/WestbrookToyota | Z85: https://twitter.com/WestbrookToyota | AA85: https://www.youtube.com/user/WestbrookToyota | AB85: https://www.yelp.com/biz/westbrook-toyota-westbrook | AE85: https://www.toyotatirecenter.com/?uid=A119DDE5-FFED-17FB-9AD0CCCC6AF5818C | AF85: 2022-04-11 | AG85: 2026-06-08 | AH85: Same as Dealer_URL (homepage) | AK85: None (no sitemap found; homepage links yielded no candidates)
A86: 06049 | B86: Toyota of Colchester | C86: 164 | D86: 860-537-2468 | E86: 100 Old Hartford Road | F86: Colchester | G86: CT | H86: 06415 | I86: https://www.toyotaofcolchester.com | J86: 24-Hour Vehicle Drop Off;Advanced Diagnostics;Advanced Tune-Up Equip.;Barista/Coffee Bar;Children's Play Area;Contactless Service;Express Lube;Parts Center;Toyota Tire Center | K86: https://www.toyotaofcolchester.com/#modal-scheduleservice | L86: Monday 7:30 am - 5:00 pm~Tuesday 7:30 am - 5:00 pm~Wednesday 7:30 am - 5:00 pm~Thursday 7:30 am - 5:00 pm~Friday 7:30 am - 5:00 pm~Saturday 7:30 am - 12:30 pm~ | M86: service@toyotaofcolchester.com | N86: John Donovan | O86: Your Service Professionals | P86: Toyota of Colchester | R86: 24-Hour Vehicle Drop Off | S86: Advanced Diagnostics | T86: Advanced Tune-Up Equip. | U86: Barista/Coffee Bar | V86: Children's Play Area | W86: Contactless Service | X86: 8605372468 | Y86: https://www.facebook.com/ToyotaofColchester | Z86: https://twitter.com/ToyotaofColch | AA86: https://www.youtube.com/user/toyotaofcolchester1 | AB86: https://www.yelp.com/biz/toyota-of-colchester-colchester | AC86: https://instagram.com/toyotaofcolchester | AE86: https://www.toyotatirecenter.com/?uid=01853974-A24D-A534-5A408B2032974A14 | AF86: 2022-04-11 | AG86: 2026-03-16 | AH86: Same as Dealer_URL (homepage) | AK86: Low (candidates found but none loaded cleanly)
A87: 06054 | B87: Crabtree Toyota | C87: 164 | D87: 203-283-3081 | E87: 832 Straits Turnpike | F87: Watertown | G87: CT | H87: 06795 | I87: https://www.crabtreetoyota.com | J87: Advanced Diagnostics;Advanced Tune-Up Equip.;Barista/Coffee Bar;Complimentary Beverages;EV Charging Station;Online Scheduling;Parts Center;Toyota Collision Center | K87: https://service.connectcdk.com/?cid=2002231 | L87: Monday 7:30 am - 5:00 pm~Tuesday 7:30 am - 5:00 pm~Wednesday 7:30 am - 5:00 pm~Thursday 7:30 am - 5:00 pm~Friday 7:30 am - 5:00 pm~Saturday 8:00 am - 3:00 pm~ | N87: Joseph Fazzina | R87: Advanced Diagnostics | S87: Advanced Tune-Up Equip. | T87: Barista/Coffee Bar | U87: Complimentary Beverages | V87: EV Charging Station | W87: Online Scheduling | X87: 2032833083 | Y87: https://www.facebook.com/crabtreetoyota/ | AC87: https://www.instagram.com/crabtreetoyota/ | AD87: https://express.crabtreetoyota.com/ | AE87: https://www.toyotatirecenter.com/?uid=E26FF549-24D5-4779-B9F0D0621DC6200E | AF87: 2022-11-22 | AG87: 2026-05-06 | AH87: 3rd Party Scheduler | AI87: Hosted on connectcdk.com, not on dealer's own domain
A88: 07008 | B88: Price Toyota | C88: 801 | D88: 302-322-8600 | E88: 168 N. Dupont Highway | F88: New Castle | G88: DE | H88: 19720 | I88: https://www.pricetoyota.com | J88: 24-Hour Vehicle Drop Off;Advanced Diagnostics;Advanced Tune-Up Equip.;Online Scheduling;Prius Plug-in Service;Shuttle Service;Auto Detailing;Parts Center;Toyota Collision Center;Toyota Tire Center | K88: https://www.pricetoyota.com/#modal-scheduleservice | M88: econnor@priceautogroup.com | N88: Ed Connor | O88: Ed Connor | P88: Service Manager | R88: 24-Hour Vehicle Drop Off | S88: Advanced Diagnostics | T88: Advanced Tune-Up Equip. | U88: Online Scheduling | V88: Prius Plug-in Service | W88: Shuttle Service | X88: 3023228600 | Y88: https://www.facebook.com/PriceToyota | Z88: https://twitter.com/PriceToyota | AA88: https://www.youtube.com/user/pricetoyota/feed | AB88: https://www.yelp.com/biz/price-toyota-scion-new-castle | AE88: https://www.toyotatirecenter.com/?uid=51402C03-E8A2-EF88-98364574B4290086 | AF88: 2022-04-11 | AG88: 2026-03-16 | AH88: Same as Dealer_URL (homepage) | AJ88: https://www.pricetoyota.com/ScheduleService | AK88: High
A89: 17070 | B89: Greg Leblanc Toyota | C89: 60G | D89: 985-876-7210 | E89: 220 S. Hollywood Road | F89: Houma | G89: LA | H89: 70360 | I89: https://www.gregleblanctoyota.com | J89: Online Scheduling;Vending Machines;WiFi Available;Express Maintenance;Parts Center;Toyota Tire Center | K89: https://www.gregleblanctoyota.com/express-service | L89: Monday 7:30 am - 6:00 pm~Tuesday 7:30 am - 6:00 pm~Wednesday 7:30 am - 6:00 pm~Thursday 7:30 am - 6:00 pm~Friday 7:30 am - 6:00 pm~~ | R89: Online Scheduling | S89: Vending Machines | T89: WiFi Available | X89: 9858767210 | Y89: https://www.facebook.com/gregleblanctoyota | Z89: https://twitter.com/gleblanctoyota | AA89: https://www.youtube.com/channel/UCaZBLqUyzWA3EYv5Q0kiEJA/about | AB89: https://www.yelp.com/biz/greg-leblanc-toyota-houma | AC89: https://www.instagram.com/gregleblanctoyota | AE89: https://www.toyotatirecenter.com/?uid=21B89956-F8D6-8321-48BD4C9092C3F700 | AF89: 2022-04-11 | AG89: 2026-05-06 | AH89: Error Page Entered | AI89: Status 403 at https://www.gregleblanctoyota.com/express-service | AK89: None (no sitemap found; homepage links yielded no candidates)
A90: 17083 | B90: All Star Toyota of Baton Rouge | C90: 60G | D90: 225-925-2525 | E90: 9150 Airline Highway | F90: Baton Rouge | G90: LA | H90: 70815 | I90: https://www.allstartoyotaofbatonrouge.com | J90: Toyota Collision Center | X90: 2259252525 | AE90: https://www.toyotatirecenter.com/?uid=B34299B1-F266-409A-B6DB0139260ECB18 | AF90: 2025-11-18 | AG90: 2025-11-24 | AH90: No URL | AJ90: https://www.allstartoyotaofbatonrouge.com/schedule-service | AK90: High
A91: 18010 | B91: Down East Toyota | C91: 176 | D91: 207-989-6400 | E91: 652 Wilson Street | F91: Brewer | G91: ME | H91: 04412 | I91: https://www.downeasttoyota.com | J91: 24-Hour Vehicle Drop Off;Advanced Diagnostics;Advanced Tune-Up Equip.;Complimentary Beverages;EV Charging Station;Online Scheduling;Auto Detailing;Express Lube;On-Site Rental Vehicles;Parts Center;State Cert. Inspection;Toyota Collision Center | K91: https://www.downeasttoyota.com/toyota-service-center/ | L91: Monday 7:00 am - 5:30 pm~Tuesday 7:00 am - 5:30 pm~Wednesday 7:00 am - 5:30 pm~Thursday 7:00 am - 5:30 pm~Friday 7:00 am - 5:30 pm~Saturday 7:00 am - 4:00 pm~ | M91: service@downeasttoyota.com | O91: Daniel Paige | P91: Service Manager | R91: 24-Hour Vehicle Drop Off | S91: Advanced Diagnostics | T91: Advanced Tune-Up Equip. | U91: Complimentary Beverages | V91: EV Charging Station | W91: Online Scheduling | X91: 2079896400 | Y91: https://www.facebook.com/downeasttoyota | Z91: https://twitter.com/downeasttoyota | AA91: https://www.youtube.com/user/DowneastToyotaScion | AB91: https://www.yelp.com/biz/downeast-toyota-brewer | AC91: https://instagram.com/downeasttoyota | AE91: https://www.toyotatirecenter.com/?uid=A0F63C96-EFA1-47CE-4CE92FB90A7C9596 | AF91: 2022-04-11 | AG91: 2026-06-08 | AH91: Error Page Entered | AI91: Status 403 at https://www.downeasttoyota.com/toyota-service-center/ | AK91: None (no sitemap found; homepage links yielded no candidates)
A92: 18038 | B92: Ira Toyota Saco | C92: 176 | D92: 207-282-6161 | E92: 783 Portland Road | F92: Saco | G92: ME | H92: 04072 | I92: https://www.iratoyotasaco.com | J92: 24-Hour Vehicle Drop Off;Advanced Diagnostics;Advanced Tune-Up Equip.;Barista/Coffee Bar;Children's Play Area;Complimentary Beverages;Auto Detailing;Car Wash;Express Lube;Mirai Service;Parts Center;RAV4 EV Service | K92: https://www.iratoyotasaco.com/service/schedule-service/ | L92: Monday 7:00 am - 7:00 pm~Tuesday 7:00 am - 7:00 pm~Wednesday 7:00 am - 7:00 pm~Thursday 7:00 am - 7:00 pm~Friday 7:30 am - 6:00 pm~Saturday 7:30 am - 5:00 pm~ | O92: Service Professionals | P92: Ira Toyota Saco | R92: 24-Hour Vehicle Drop Off | S92: Advanced Diagnostics | T92: Advanced Tune-Up Equip. | U92: Barista/Coffee Bar | V92: Children's Play Area | W92: Complimentary Beverages | X92: 2072826161 | AE92: https://www.toyotatirecenter.com/?uid=9EB689FC-A7CE-6DFB-9796D5399BF0B9F9 | AF92: 2022-04-11 | AG92: 2026-07-07 | AH92: Unreachable / Timeout | AI92: ('Connection aborted.', RemoteDisconnected('Remote end closed connection without response')) | browser fallback unavailable: Page.goto: Timeout 20000ms exceeded. Call log: - navigating to "https://w
A93: 19028 | B93: Younger Toyota | C93: 803 | D93: 301-733-2300 | E93: 1945 Dual Highway | F93: Hagerstown | G93: MD | H93: 21740 | I93: https://www.youngertoyota.com | J93: 24-Hour Vehicle Drop Off;Advanced Diagnostics;Advanced Tune-Up Equip.;Online Scheduling;Prius Plug-in Service;Shuttle Service;Auto Detailing;Parts Center;Toyota Tire Center | K93: https://www.youngertoyota.com/#schedule-service | L93: Monday 7:30 am - 6:00 pm~Tuesday 7:30 am - 6:00 pm~Wednesday 7:30 am - 6:00 pm~Thursday 7:30 am - 6:00 pm~Friday 7:30 am - 6:00 pm~Saturday 8:00 am - 5:00 pm~ | M93: service@youngertoyota.com | N93: Brandon Humbertson | O93: Brandon Humbertson | P93: Service Manager | R93: 24-Hour Vehicle Drop Off | S93: Advanced Diagnostics | T93: Advanced Tune-Up Equip. | U93: Online Scheduling | V93: Prius Plug-in Service | W93: Shuttle Service | X93: 3017332300 | Y93: https://www.facebook.com/youngerauto | Z93: https://twitter.com/Younger_Toyota | AA93: https://www.youtube.com/user/youngertoyotascion | AB93: https://www.yelp.com/biz/younger-toyota-hagerstown-4 | AC93: https://www.instagram.com/youngertoyota/ | AE93: https://www.toyotatirecenter.com/?uid=A665AEAC-0BBB-E33F-DC0D48E74F62D7F7 | AF93: 2022-04-11 | AG93: 2026-03-16 | AH93: Same as Dealer_URL (homepage) | AJ93: https://www.youngertoyota.com/schedule-service/ | AK93: High
A94: 19063 | B94: DARCARS Toyota of Frederick | C94: 803 | D94: 301-696-6300 | E94: 5293 Buckeystown Pike | F94: Frederick | G94: MD | H94: 21704 | I94: https://www.darcarstoyotaoffrederick.com | J94: 24-Hour Vehicle Drop Off;Advanced Diagnostics;Advanced Tune-Up Equip.;Barista/Coffee Bar;Children's Play Area;Contactless Service;Auto Detailing;Car Wash;Express Lube;Express Maintenance;On-Site Rental Vehicles;Parts Center | K94: https://www.darcarstoyotaoffrederick.com/Two-Service-Locations.html | L94: Monday 7:00 am - 8:00 pm~Tuesday 7:00 am - 8:00 pm~Wednesday 7:00 am - 8:00 pm~Thursday 7:00 am - 8:00 pm~Friday 7:00 am - 8:00 pm~Saturday 8:00 am - 4:00 pm~ | M94: donald.mcneely@darcars.com | O94: Darcars Customer Relations Team | R94: 24-Hour Vehicle Drop Off | S94: Advanced Diagnostics | T94: Advanced Tune-Up Equip. | U94: Barista/Coffee Bar | V94: Children's Play Area | W94: Contactless Service | X94: 3016966300 | Y94: https://www.facebook.com/DARCARSToyotaofFrederick | Z94: https://twitter.com/toyotafrederick | AA94: https://www.youtube.com/channel/UCuoB4-08-NGBMd4yGsksICw | AB94: https://www.yelp.com/biz/darcars-toyota-scion-frederick-frederick-7 | AE94: https://www.toyotatirecenter.com/?uid=DEC0E510-CF3D-EEFD-1C9BDE2805CE446D | AF94: 2022-04-11 | AG94: 2026-07-07 | AH94: No Issue Detected
A95: 19069 | B95: DARCARS Toyota of Baltimore | C95: 802 | D95: 410-633-8800 | E95: 6007 Eastern Avenue | F95: Baltimore | G95: MD | H95: 21224 | I95: https://www.darcarstoyotaofbaltimore.com | J95: 24-Hour Vehicle Drop Off;Advanced Diagnostics;Advanced Tune-Up Equip.;Barista/Coffee Bar;Complimentary Beverages;EV Charging Station;Auto Detailing;Car Wash;Express Lube;Express Maintenance;On-Site Rental Vehicles;Parts Center | K95: https://www.darcarstoyotaofbaltimore.com/#schedule-service | L95: Monday 7:00 am - 6:00 pm~Tuesday 7:00 am - 6:00 pm~Wednesday 7:00 am - 6:00 pm~Thursday 7:00 am - 6:00 pm~Friday 7:00 am - 6:00 pm~Saturday 8:00 am - 4:00 pm~ | M95: darcarstoyotabaltimore@leadmachine.dealer.com | O95: Darcars Customer Relations Team | R95: 24-Hour Vehicle Drop Off | S95: Advanced Diagnostics | T95: Advanced Tune-Up Equip. | U95: Barista/Coffee Bar | V95: Complimentary Beverages | W95: EV Charging Station | X95: 4106332200 | Y95: https://www.facebook.com/DARCARSToyotaBaltimore/timeline | Z95: https://twitter.com/toyotabaltimore | AA95: https://www.youtube.com/channel/UCmfvZnqP9OG1anirPDGhnaw/featured | AB95: https://www.yelp.com/biz/darcars-toyota-scion-baltimore-baltimore-8 | AC95: https://instagram.com/darcars_toyota | AE95: https://www.toyotatirecenter.com/?uid=9C74C8AE-93E0-675D-4D782527ED56D38D | AF95: 2022-04-11 | AG95: 2026-07-07 | AH95: Same as Dealer_URL (homepage) | AJ95: https://www.darcarstoyotaofbaltimore.com/#schedule-service | AK95: High
A96: 19075 | B96: Hertrich Toyota of Pocomoke | C96: 805 | D96: 410-957-2222 | E96: 1337 Ocean Highway | F96: Pocomoke City | G96: MD | H96: 21851 | I96: https://www.hertrichtoyotapocomoke.com | J96: 24-Hour Vehicle Drop Off;Advanced Diagnostics;Advanced Tune-Up Equip.;Online Scheduling;Shuttle Service;Toyota Cert. Technicians;Auto Detailing;Parts Center | K96: https://www.hertrichtoyotapocomoke.com/scheduler-service-online.htm | L96: Monday 7:30 am - 5:30 pm~Tuesday 7:30 am - 5:30 pm~Wednesday 7:30 am - 5:30 pm~Thursday 7:30 am - 5:30 pm~Friday 7:30 am - 5:30 pm~Saturday 8:00 am - 1:00 pm~ | O96: Your Toyota Service Professionals | R96: 24-Hour Vehicle Drop Off | S96: Advanced Diagnostics | T96: Advanced Tune-Up Equip. | U96: Online Scheduling | V96: Shuttle Service | W96: Toyota Cert. Technicians | X96: 4109574444 | Y96: https://www.facebook.com/hertrichtoyotaofpocomoke/ | AE96: https://www.toyotatirecenter.com/?uid=8CC885CB-6751-474A-864DE197A62569C3 | AF96: 2022-04-11 | AG96: 2026-05-06 | AH96: No Issue Detected
A97: 19079 | B97: Koons Toyota Annapolis | C97: 802 | D97: 410-268-6480 | E97: 1013 West Street | F97: Annaplis | G97: MD | H97: 21401 | I97: https://www.koonstoyotaannapolis.com | J97: Express Maintenance | K97: https://www.koonstoyotaannapolis.com/schedule-service.html | L97: Monday 7:00 am - 7:00 pm~Tuesday 7:00 am - 7:00 pm~Wednesday 7:00 am - 7:00 pm~Thursday 7:00 am - 7:00 pm~Friday 7:00 am - 7:00 pm~Saturday 7:00 am - 5:00 pm~ | X97: 4102686480 | AE97: https://www.toyotatirecenter.com/?uid=982CAB96-9FD4-BED4-FC0895FA287032B3 | AF97: 2023-12-12 | AG97: 2026-06-08 | AH97: No Issue Detected
A98: 19090 | B98: Waldorf Toyota | C98: 803 | D98: 301-843-3700 | E98: 2600 Crain Highway | F98: Waldorf | G98: MD | H98: 20601 | I98: https://www.waldorftoyota.com | L98: Monday 7:00 am - 6:00 pm~Tuesday 7:00 am - 6:00 pm~Wednesday 7:00 am - 6:00 pm~Thursday 7:00 am - 6:00 pm~Friday 7:00 am - 6:00 pm~Saturday 7:00 am - 4:00 pm~ | X98: 3018433700 | AE98: https://www.toyotatirecenter.com/?uid=4488FE85-4B59-46A2-B492DAC2EBFC91FC | AF98: 2026-03-06 | AG98: 2026-07-07 | AH98: No URL | AJ98: https://www.waldorftoyota.com/scheduleservice.html | AK98: High
A99: 20016 | B99: Balise Toyota | C99: 175 | D99: 413-731-8500 | E99: 1399 Riverdale Street | F99: West Springfield | G99: MA | H99: 01089 | I99: https://www.balisetoyota.com/ | J99: 24-Hour Vehicle Drop Off;Advanced Diagnostics;Advanced Tune-Up Equip.;Barista/Coffee Bar;Online Scheduling;Prius Plug-in Service;Parts Center;State Cert. Inspection;Toyota Collision Center;Toyota Tire Center | K99: https://www.balisetoyota.com/schedule-appointment.html | L99: Monday 8:00 am - 5:30 pm~Tuesday 8:00 am - 5:30 pm~Wednesday 8:00 am - 5:30 pm~Thursday 8:00 am - 5:30 pm~Friday 8:00 am - 5:30 pm~Saturday 8:00 am - 4:00 pm~ | M99: web-btoservice@baliseauto.com | N99: Amanda Roy | O99: Your Service Professionals | P99: Balise Toyota | R99: 24-Hour Vehicle Drop Off | S99: Advanced Diagnostics | T99: Advanced Tune-Up Equip. | U99: Barista/Coffee Bar | V99: Online Scheduling | W99: Prius Plug-in Service | X99: 4137348795 | Y99: https://www.facebook.com/BaliseToyota | Z99: https://twitter.com/baliseautogroup | AA99: https://www.youtube.com/channel/UCk_tYb1RCB983-kBDBrBMEA | AB99: https://www.yelp.com/biz/balise-toyota-scion-west-springfield | AF99: 2022-04-11 | AG99: 2025-06-04 | AH99: No Issue Detected
A100: 20102 | B100: Lexington Toyota | C100: 171 | D100: 781-861-7400 | E100: 409 Massachusetts Avenue | F100: Lexington | G100: MA | H100: 02420 | I100: https://www.lexingtontoyota.com | J100: 24-Hour Vehicle Drop Off;Advanced Diagnostics;Advanced Tune-Up Equip.;Online Scheduling;Prius Plug-in Service;Shuttle Service;Auto Detailing;Parts Center;State Cert. Inspection;Toyota Tire Center | K100: https://www.lexingtontoyota.com/service/schedule-service | L100: Monday 7:30 am - 6:00 pm~Tuesday 7:30 am - 6:00 pm~Wednesday 7:30 am - 6:00 pm~Thursday 7:30 am - 6:00 pm~Friday 7:30 am - 6:00 pm~Saturday 7:30 am - 5:00 pm~ | M100: service@lexingtontoyota.com | N100: Mike Schiavone | O100: Service Professionals | P100: Lexington Toyota | R100: 24-Hour Vehicle Drop Off | S100: Advanced Diagnostics | T100: Advanced Tune-Up Equip. | U100: Online Scheduling | V100: Prius Plug-in Service | W100: Shuttle Service | X100: 7818617400 | Y100: https://www.facebook.com/George-Greys-Lexington-Toyota-283225168377017 | Z100: https://twitter.com/LexingtonToyota | AA100: https://www.youtube.com/user/LexingtonToyota | AB100: https://www.yelp.com/biz/lexington-toyota-lexington-2 | AC100: https://lexingtontoyota.com | AE100: https://www.toyotatirecenter.com/?uid=3985E742-A9ED-5C41-13CB786F9627FFC2 | AF100: 2022-04-11 | AG100: 2026-06-08 | AH100: No Issue Detected
...

Sheet Summary
A1: Error Type | B1: Count | C1: New Error | D1: Comments | E1: Count of suggested URL | I1: Comments
E2: High | F2: Medium | G2: Low | H2: None
A3: {=_xlfn._xlws.SORT(_xlfn.UNIQUE(_xlfn._xlws.FILTER('AMP Dealer Profile Data'!AH:AH,'AMP Dealer Profile Data'!AH:AH<>"")))} -> 3rd Party Scheduler | B3: =COUNTIF('AMP Dealer Profile Data'!AH:AH,A3) -> 23 | D3: Only listed domains are identified | E3: =COUNTIFS('AMP Dealer Profile Data'!$AH:$AH,$A3,'AMP Dealer Profile Data'!$AK:$AK,"High") -> 0 | F3: =COUNTIFS('AMP Dealer Profile Data'!$AH:$AH,$A3,'AMP Dealer Profile Data'!$AK:$AK,"Medium") -> 0 | G3: =COUNTIFS('AMP Dealer Profile Data'!$AH:$AH,$A3,'AMP Dealer Profile Data'!$AK:$AK,"Low (candidates found but none loaded cleanly)") -> 0 | H3: =COUNTIFS('AMP Dealer Profile Data'!$AH:$AH,$A3,'AMP Dealer Profile Data'!$AK:$AK,"None (no sitemap found; homepage links yielded no candidates)") -> 0
A4: Different Domain (Unverified) | B4: =COUNTIF('AMP Dealer Profile Data'!AH:AH,A4) -> 43 | C4: Yes | D4: The service URL is redirecting to the actual domain but is not identified | E4: =COUNTIFS('AMP Dealer Profile Data'!$AH:$AH,$A4,'AMP Dealer Profile Data'!$AK:$AK,"High") -> 0 | F4: =COUNTIFS('AMP Dealer Profile Data'!$AH:$AH,$A4,'AMP Dealer Profile Data'!$AK:$AK,"Medium") -> 0 | G4: =COUNTIFS('AMP Dealer Profile Data'!$AH:$AH,$A4,'AMP Dealer Profile Data'!$AK:$AK,"Low (candidates found but none loaded cleanly)") -> 0 | H4: =COUNTIFS('AMP Dealer Profile Data'!$AH:$AH,$A4,'AMP Dealer Profile Data'!$AK:$AK,"None (no sitemap found; homepage links yielded no candidates)") -> 0
A5: Error Page Entered | B5: =COUNTIF('AMP Dealer Profile Data'!AH:AH,A5) -> 159 | E5: =COUNTIFS('AMP Dealer Profile Data'!$AH:$AH,$A5,'AMP Dealer Profile Data'!$AK:$AK,"High") -> 30 | F5: =COUNTIFS('AMP Dealer Profile Data'!$AH:$AH,$A5,'AMP Dealer Profile Data'!$AK:$AK,"Medium") -> 10 | G5: =COUNTIFS('AMP Dealer Profile Data'!$AH:$AH,$A5,'AMP Dealer Profile Data'!$AK:$AK,"Low (candidates found but none loaded cleanly)") -> 2 | H5: =COUNTIFS('AMP Dealer Profile Data'!$AH:$AH,$A5,'AMP Dealer Profile Data'!$AK:$AK,"None (no sitemap found; homepage links yielded no candidates)") -> 117
A6: Error_Type | B6: =COUNTIF('AMP Dealer Profile Data'!AH:AH,A6) -> 1 | E6: =COUNTIFS('AMP Dealer Profile Data'!$AH:$AH,$A6,'AMP Dealer Profile Data'!$AK:$AK,"High") -> 0 | F6: =COUNTIFS('AMP Dealer Profile Data'!$AH:$AH,$A6,'AMP Dealer Profile Data'!$AK:$AK,"Medium") -> 0 | G6: =COUNTIFS('AMP Dealer Profile Data'!$AH:$AH,$A6,'AMP Dealer Profile Data'!$AK:$AK,"Low (candidates found but none loaded cleanly)") -> 0 | H6: =COUNTIFS('AMP Dealer Profile Data'!$AH:$AH,$A6,'AMP Dealer Profile Data'!$AK:$AK,"None (no sitemap found; homepage links yielded no candidates)") -> 0
A7: No Issue Detected | B7: =COUNTIF('AMP Dealer Profile Data'!AH:AH,A7) -> 620 | E7: =COUNTIFS('AMP Dealer Profile Data'!$AH:$AH,$A7,'AMP Dealer Profile Data'!$AK:$AK,"High") -> 0 | F7: =COUNTIFS('AMP Dealer Profile Data'!$AH:$AH,$A7,'AMP Dealer Profile Data'!$AK:$AK,"Medium") -> 0 | G7: =COUNTIFS('AMP Dealer Profile Data'!$AH:$AH,$A7,'AMP Dealer Profile Data'!$AK:$AK,"Low (candidates found but none loaded cleanly)") -> 0 | H7: =COUNTIFS('AMP Dealer Profile Data'!$AH:$AH,$A7,'AMP Dealer Profile Data'!$AK:$AK,"None (no sitemap found; homepage links yielded no candidates)") -> 0
A8: No URL | B8: =COUNTIF('AMP Dealer Profile Data'!AH:AH,A8) -> 58 | E8: =COUNTIFS('AMP Dealer Profile Data'!$AH:$AH,$A8,'AMP Dealer Profile Data'!$AK:$AK,"High") -> 50 | F8: =COUNTIFS('AMP Dealer Profile Data'!$AH:$AH,$A8,'AMP Dealer Profile Data'!$AK:$AK,"Medium") -> 4 | G8: =COUNTIFS('AMP Dealer Profile Data'!$AH:$AH,$A8,'AMP Dealer Profile Data'!$AK:$AK,"Low (candidates found but none loaded cleanly)") -> 0 | H8: =COUNTIFS('AMP Dealer Profile Data'!$AH:$AH,$A8,'AMP Dealer Profile Data'!$AK:$AK,"None (no sitemap found; homepage links yielded no candidates)") -> 4
A9: Query String Dropped on Append | B9: =COUNTIF('AMP Dealer Profile Data'!AH:AH,A9) -> 1 | E9: =COUNTIFS('AMP Dealer Profile Data'!$AH:$AH,$A9,'AMP Dealer Profile Data'!$AK:$AK,"High") -> 0 | F9: =COUNTIFS('AMP Dealer Profile Data'!$AH:$AH,$A9,'AMP Dealer Profile Data'!$AK:$AK,"Medium") -> 0 | G9: =COUNTIFS('AMP Dealer Profile Data'!$AH:$AH,$A9,'AMP Dealer Profile Data'!$AK:$AK,"Low (candidates found but none loaded cleanly)") -> 0 | H9: =COUNTIFS('AMP Dealer Profile Data'!$AH:$AH,$A9,'AMP Dealer Profile Data'!$AK:$AK,"None (no sitemap found; homepage links yielded no candidates)") -> 0
A10: Query String Renders Error Page | B10: =COUNTIF('AMP Dealer Profile Data'!AH:AH,A10) -> 5 | D10: Redirection in the base URL itself; the append does not follow that same redirect, leading to error | E10: =COUNTIFS('AMP Dealer Profile Data'!$AH:$AH,$A10,'AMP Dealer Profile Data'!$AK:$AK,"High") -> 0 | F10: =COUNTIFS('AMP Dealer Profile Data'!$AH:$AH,$A10,'AMP Dealer Profile Data'!$AK:$AK,"Medium") -> 0 | G10: =COUNTIFS('AMP Dealer Profile Data'!$AH:$AH,$A10,'AMP Dealer Profile Data'!$AK:$AK,"Low (candidates found but none loaded cleanly)") -> 0 | H10: =COUNTIFS('AMP Dealer Profile Data'!$AH:$AH,$A10,'AMP Dealer Profile Data'!$AK:$AK,"None (no sitemap found; homepage links yielded no candidates)") -> 0
A11: Query String Test Failed (network error) | B11: =COUNTIF('AMP Dealer Profile Data'!AH:AH,A11) -> 2 | C11: Yes | D11: Subject to change with each validation | E11: =COUNTIFS('AMP Dealer Profile Data'!$AH:$AH,$A11,'AMP Dealer Profile Data'!$AK:$AK,"High") -> 0 | F11: =COUNTIFS('AMP Dealer Profile Data'!$AH:$AH,$A11,'AMP Dealer Profile Data'!$AK:$AK,"Medium") -> 0 | G11: =COUNTIFS('AMP Dealer Profile Data'!$AH:$AH,$A11,'AMP Dealer Profile Data'!$AK:$AK,"Low (candidates found but none loaded cleanly)") -> 0 | H11: =COUNTIFS('AMP Dealer Profile Data'!$AH:$AH,$A11,'AMP Dealer Profile Data'!$AK:$AK,"None (no sitemap found; homepage links yielded no candidates)") -> 0
A12: Redirect Drops Query String | B12: =COUNTIF('AMP Dealer Profile Data'!AH:AH,A12) -> 167 | E12: =COUNTIFS('AMP Dealer Profile Data'!$AH:$AH,$A12,'AMP Dealer Profile Data'!$AK:$AK,"High") -> 0 | F12: =COUNTIFS('AMP Dealer Profile Data'!$AH:$AH,$A12,'AMP Dealer Profile Data'!$AK:$AK,"Medium") -> 0 | G12: =COUNTIFS('AMP Dealer Profile Data'!$AH:$AH,$A12,'AMP Dealer Profile Data'!$AK:$AK,"Low (candidates found but none loaded cleanly)") -> 0 | H12: =COUNTIFS('AMP Dealer Profile Data'!$AH:$AH,$A12,'AMP Dealer Profile Data'!$AK:$AK,"None (no sitemap found; homepage links yielded no candidates)") -> 0
A13: Same as Dealer_URL (homepage) | B13: =COUNTIF('AMP Dealer Profile Data'!AH:AH,A13) -> 163 | D13: In some cases, the service module is refferenced within the homepage. The suggested URL may differ or remain the same in the case of single-page websites | E13: =COUNTIFS('AMP Dealer Profile Data'!$AH:$AH,$A13,'AMP Dealer Profile Data'!$AK:$AK,"High") -> 141 | F13: =COUNTIFS('AMP Dealer Profile Data'!$AH:$AH,$A13,'AMP Dealer Profile Data'!$AK:$AK,"Medium") -> 8 | G13: =COUNTIFS('AMP Dealer Profile Data'!$AH:$AH,$A13,'AMP Dealer Profile Data'!$AK:$AK,"Low (candidates found but none loaded cleanly)") -> 9 | H13: =COUNTIFS('AMP Dealer Profile Data'!$AH:$AH,$A13,'AMP Dealer Profile Data'!$AK:$AK,"None (no sitemap found; homepage links yielded no candidates)") -> 4 | I13: In some cases, the service module is refferenced within the homepage. The suggested URL may differ or remain the same in the case of single-page websites
A14: Tracking Appends Entered | B14: =COUNTIF('AMP Dealer Profile Data'!AH:AH,A14) -> 2 | E14: =COUNTIFS('AMP Dealer Profile Data'!$AH:$AH,$A14,'AMP Dealer Profile Data'!$AK:$AK,"High") -> 0 | F14: =COUNTIFS('AMP Dealer Profile Data'!$AH:$AH,$A14,'AMP Dealer Profile Data'!$AK:$AK,"Medium") -> 0 | G14: =COUNTIFS('AMP Dealer Profile Data'!$AH:$AH,$A14,'AMP Dealer Profile Data'!$AK:$AK,"Low (candidates found but none loaded cleanly)") -> 0 | H14: =COUNTIFS('AMP Dealer Profile Data'!$AH:$AH,$A14,'AMP Dealer Profile Data'!$AK:$AK,"None (no sitemap found; homepage links yielded no candidates)") -> 0
A15: Unreachable / Timeout | B15: =COUNTIF('AMP Dealer Profile Data'!AH:AH,A15) -> 25 | C15: Yes | D15: Subject to change with each validation | E15: =COUNTIFS('AMP Dealer Profile Data'!$AH:$AH,$A15,'AMP Dealer Profile Data'!$AK:$AK,"High") -> 0 | F15: =COUNTIFS('AMP Dealer Profile Data'!$AH:$AH,$A15,'AMP Dealer Profile Data'!$AK:$AK,"Medium") -> 0 | G15: =COUNTIFS('AMP Dealer Profile Data'!$AH:$AH,$A15,'AMP Dealer Profile Data'!$AK:$AK,"Low (candidates found but none loaded cleanly)") -> 0 | H15: =COUNTIFS('AMP Dealer Profile Data'!$AH:$AH,$A15,'AMP Dealer Profile Data'!$AK:$AK,"None (no sitemap found; homepage links yielded no candidates)") -> 0
